{
	"㐵":"9277",
	"㑀":"96DF",
	"㑊":"8CF4",
	"㑌":"89D5",
	"㑤":"93CD",
	"㑳":"9BDF",
	"㑺":"FA68",
	"㑽":"89DA",
	"㑾":"8F59",
	"㒓":"89DB",
	"㒖":"8F5D",
	"㒥":"89DC",
	"㒯":"96F7",
	"㒼":"8ADA",
	"㓁":"8BDC",
	"㓈":"97DB",
	"㓟":"9E53",
	"㓤":"9DAA",
	"㓦":"87BE",
	"㓻":"9BEA",
	"㔆":"8A6E",
	"㔾":"8BC8",
	"㕑":"89E8",
	"㕓":"89EA",
	"㕙":"8C4B",
	"㕡":"FB70",
	"㕭":"89ED",
	"㕰":"94DD",
	"㕲":"89EE",
	"㕷":"9EB4",
	"㕸":"8AD3",
	"㖄":"92DB",
	"㖗":"94DB",
	"㖘":"89F9",
	"㖡":"FB7A",
	"㖥":"89FB",
	"㖭":"9EFC",
	"㖿":"89FC",
	"㗁":"89BF",
	"㗅":"89FE",
	"㗇":"89E6",
	"㗊":"9D46",
	"㗎":"9DEE",
	"㗒":"A07E",
	"㗖":"A068",
	"㗛":"98E9",
	"㗝":"8B68",
	"㗱":"8DFD",
	"㗲":"8BBE",
	"㗳":"9FD9",
	"㗻":"8AEB",
	"㗾":"9FD7",
	"㘉":"8B6A",
	"㘘":"9C5C",
	"㘚":"8BB1",
	"㘣":"FB5E",
	"㘥":"8770",
	"㘭":"9DF3",
	"㘵":"A0D0",
	"㘹":"FC66",
	"㘾":"92E9",
	"㙇":"9AEC",
	"㙈":"8FAB",
	"㙉":"FA48",
	"㙎":"8E45",
	"㙟":"9C6F",
	"㙡":"8D5C",
	"㙺":"9EDE",
	"㚁":"89EF",
	"㚚":"96E9",
	"㚥":"9EBB",
	"㚪":"94DE",
	"㚬":"9EB8",
	"㚰":"97BA",
	"㚱":"FB65",
	"㚵":"95D6",
	"㚹":"9CBB",
	"㚼":"97DA",
	"㛁":"8F45",
	"㛃":"FB7D",
	"㛄":"9158",
	"㛅":"FE64",
	"㛇":"9856",
	"㛈":"9B4D",
	"㛓":"935B",
	"㛔":"95C7",
	"㛖":"97E7",
	"㛝":"9359",
	"㛡":"91F5",
	"㛢":"97B8",
	"㛥":"FDA2",
	"㛦":"FBB6",
	"㛵":"92FA",
	"㜁":"9357",
	"㜃":"8BA6",
	"㜈":"FBB9",
	"㜊":"97B0",
	"㜍":"FDC4",
	"㜜":"9CA1",
	"㜢":"91F2",
	"㜣":"91F9",
	"㜥":"8FF1",
	"㜬":"9745",
	"㜭":"9853",
	"㜰":"FE78",
	"㜲":"FBC1",
	"㜳":"9251",
	"㜺":"9DAD",
	"㝀":"FD6C",
	"㝃":"FA6B",
	"㝢":"9BC2",
	"㝯":"9A7B",
	"㞗":"8B60",
	"㞠":"934B",
	"㞹":"9ABD",
	"㞾":"91B7",
	"㟖":"8D4B",
	"㟲":"95B4",
	"㟸":"FEC5",
	"㟻":"9EF0",
	"㠏":"8D64",
	"㠙":"9269",
	"㠠":"8D67",
	"㠭":"FBEA",
	"㠶":"FBEF",
	"㠸":"8D68",
	"㡣":"93EB",
	"㡵":"877A",
	"㢠":"FC42",
	"㣃":"9166",
	"㣌":"FACD",
	"㣑":"93DD",
	"㣔":"8D52",
	"㣺":"8BCC",
	"㤈":"8D6D",
	"㤔":"8D6E",
	"㤧":"96A8",
	"㤲":"FCA6",
	"㤿":"8D6F",
	"㥍":"8D70",
	"㥣":"FC64",
	"㥸":"8CF3",
	"㦀":"9060",
	"㦉":"8D74",
	"㦊":"97C3",
	"㦒":"8AD0",
	"㦙":"9274",
	"㦛":"9BBE",
	"㦡":"9CC8",
	"㦤":"9CBA",
	"㦸":"8D78",
	"㧜":"9EB9",
	"㧢":"955A",
	"㧥":"91B4",
	"㧬":"8A48",
	"㧸":"8D7D",
	"㧻":"8A7D",
	"㧾":"8AC2",
	"㨁":"FD4A",
	"㨃":"8DA1",
	"㨆":"8AD1",
	"㨗":"FCB4",
	"㨘":"8B47",
	"㨩":"93A4",
	"㨪":"9EDA",
	"㨴":"8A51",
	"㩋":"8DA6",
	"㩒":"9EC5",
	"㩗":"FCC4",
	"㩜":"A078",
	"㩞":"94B5",
	"㩦":"FCC2",
	"㩧":"8A6B",
	"㪗":"8DAB",
	"㪫":"FAE8",
	"㪽":"8DAD",
	"㫞":"FC49",
	"㫠":"93C1",
	"㫰":"906F",
	"㫲":"8DB0",
	"㫵":"87A2",
	"㫻":"947E",
	"㬎":"90FA",
	"㬙":"9479",
	"㬢":"8DB2",
	"㬫":"FCEE",
	"㬹":"997B",
	"㭂":"8DB4",
	"㭘":"8DB7",
	"㭠":"91B3",
	"㭱":"8DBB",
	"㭲":"8DBA",
	"㭻":"8DBC",
	"㭼":"9044",
	"㮀":"FD4C",
	"㮕":"874B",
	"㮖":"93E4",
	"㮙":"93E0",
	"㮡":"FD53",
	"㮼":"8DC3",
	"㮾":"9BB8",
	"㯂":"FBF0",
	"㯄":"93E9",
	"㯗":"93F6",
	"㯝":"8DC5",
	"㯬":"8DCA",
	"㯲":"8DCC",
	"㯳":"FD5D",
	"㯴":"93B5",
	"㰍":"FD61",
	"㰑":"9CF8",
	"㰕":"9252",
	"㰘":"A0E8",
	"㱔":"9CA5",
	"㲋":"8C56",
	"㳋":"8DD6",
	"㳍":"97C0",
	"㳑":"A0DE",
	"㳖":"97D2",
	"㳜":"FAA5",
	"㳫":"FDA3",
	"㳯":"8DDB",
	"㴒":"8CEA",
	"㴓":"8EAF",
	"㴝":"91B5",
	"㴲":"FD49",
	"㴻":"FDD1",
	"㵆":"8DEB",
	"㵌":"97C6",
	"㵎":"FDCE",
	"㵑":"90FC",
	"㵟":"FC59",
	"㵢":"96D6",
	"㵩":"97C5",
	"㵪":"8DEF",
	"㵯":"97D7",
	"㵵":"8DF0",
	"㵽":"96A6",
	"㶅":"FBBF",
	"㶈":"8CDF",
	"㶊":"8DF3",
	"㶏":"9449",
	"㶑":"8DF5",
	"㶥":"9872",
	"㶭":"8E6B",
	"㶴":"FAFD",
	"㶿":"8F50",
	"㷆":"9DCC",
	"㷇":"FC65",
	"㷉":"8C44",
	"㷌":"996E",
	"㷍":"94A1",
	"㷓":"8F63",
	"㷛":"A0DA",
	"㷧":"9253",
	"㷨":"FDE9",
	"㷫":"9DB5",
	"㷳":"9879",
	"㷴":"876A",
	"㷷":"9D5D",
	"㷼":"8D63",
	"㷽":"9669",
	"㸆":"9F70",
	"㹀":"FC6A",
	"㹃":"8AC7",
	"㹈":"89D7",
	"㹕":"FE4D",
	"㹴":"9EDD",
	"㺨":"FEFB",
	"㺩":"98BC",
	"㺪":"FACC",
	"㺭":"95B0",
	"㺱":"9464",
	"㺸":"936F",
	"㺿":"94B9",
	"㻂":"95EC",
	"㻇":"91EE",
	"㻊":"98C3",
	"㻌":"95F6",
	"㻐":"8FFD",
	"㻑":"98C5",
	"㻖":"9766",
	"㻗":"FE6E",
	"㻚":"97DD",
	"㻛":"8CAA",
	"㻞":"92D2",
	"㻡":"9761",
	"㻢":"98CB",
	"㻧":"95F0",
	"㻩":"975D",
	"㻫":"91E3",
	"㻬":"877E",
	"㻰":"98CC",
	"㻳":"9469",
	"㻴":"98CD",
	"㻺":"98CE",
	"㻼":"95FC",
	"㻿":"94A3",
	"㼀":"9662",
	"㼄":"FEB6",
	"㼆":"9463",
	"㼇":"8D47",
	"㼎":"98D0",
	"㽓":"98D1",
	"㽘":"9475",
	"㽙":"FAE0",
	"㽣":"9472",
	"㽼":"98D6",
	"㾓":"8AF0",
	"㿀":"98D9",
	"㿈":"8D5A",
	"㿗":"98DB",
	"㿜":"98DD",
	"㿥":"98A8",
	"㿭":"8A6D",
	"㿹":"8AFB",
	"㿺":"8AAE",
	"䀄":"FBC9",
	"䀉":"8C5D",
	"䀝":"98E4",
	"䀹":"98E6",
	"䁅":"98E8",
	"䁓":"8A4D",
	"䁗":"9257",
	"䁢":"95DF",
	"䁥":"A0AC",
	"䁪":"98EB",
	"䁯":"98EC",
	"䁱":"8CC3",
	"䂨":"98F4",
	"䂴":"87D9",
	"䂻":"8AB8",
	"䂿":"9EE7",
	"䃈":"94BC",
	"䃘":"FCD1",
	"䃟":"9CC6",
	"䃸":"8D4A",
	"䃺":"9E7E",
	"䄂":"8D44",
	"䄃":"98FE",
	"䄄":"FDE8",
	"䄉":"9940",
	"䄎":"94C9",
	"䄱":"87C6",
	"䄲":"94D3",
	"䅧":"9946",
	"䅬":"90C0",
	"䅮":"94D1",
	"䅼":"8D4E",
	"䅿":"9573",
	"䆁":"87CE",
	"䆐":"93C2",
	"䆲":"9948",
	"䇄":"994B",
	"䇊":"8E55",
	"䇏":"994E",
	"䇛":"8EFE",
	"䇭":"8D5F",
	"䇯":"8E59",
	"䇹":"94EC",
	"䈑":"94EF",
	"䈣":"8C60",
	"䉀":"8F74",
	"䉠":"9955",
	"䉪":"9544",
	"䉶":"8CCB",
	"䉺":"9956",
	"䊌":"9959",
	"䊔":"995B",
	"䊢":"8CC4",
	"䊵":"FA45",
	"䊹":"90B7",
	"䊼":"9743",
	"䋴":"95CD",
	"䋻":"97C9",
	"䋼":"FD50",
	"䌊":"87AA",
	"䌫":"8EB9",
	"䍮":"95C6",
	"䎗":"9967",
	"䎚":"8CE3",
	"䎺":"8AB9",
	"䏁":"8DFC",
	"䏙":"8A76",
	"䏟":"9D51",
	"䏭":"9973",
	"䏰":"8740",
	"䏲":"9D4F",
	"䐁":"997A",
	"䐂":"9564",
	"䐓":"99A1",
	"䐥":"99A5",
	"䐭":"99A7",
	"䑺":"8EED",
	"䒏":"99AD",
	"䒑":"C87E",
	"䒟":"946E",
	"䒠":"8F70",
	"䒢":"FAD0",
	"䒰":"99B3",
	"䒷":"A053",
	"䒽":"8D5E",
	"䓀":"965C",
	"䓃":"8CE0",
	"䓅":"FD7A",
	"䓎":"97FE",
	"䓝":"92BD",
	"䓞":"8D5D",
	"䓟":"97FD",
	"䓡":"87DB",
	"䓤":"8F64",
	"䓩":"FCF7",
	"䓪":"9562",
	"䓫":"97CD",
	"䓬":"9E64",
	"䓴":"924C",
	"䔃":"8EC9",
	"䔄":"99BC",
	"䔉":"9DA5",
	"䔋":"8F54",
	"䔖":"8F7C",
	"䔛":"8D55",
	"䔝":"8EA2",
	"䔧":"8F7A",
	"䔮":"97AE",
	"䔳":"96C8",
	"䔶":"8CE4",
	"䔻":"99C3",
	"䔽":"90D6",
	"䔿":"9CBE",
	"䕃":"8F76",
	"䕑":"9470",
	"䕒":"FB4B",
	"䕕":"FDCA",
	"䕘":"8CEF",
	"䕜":"8EC7",
	"䕡":"8D54",
	"䕢":"A0F9",
	"䕪":"8FA9",
	"䕭":"8D51",
	"䕷":"99C7",
	"䕸":"8744",
	"䖅":"90D7",
	"䖦":"8743",
	"䖳":"8747",
	"䗚":"8758",
	"䗩":"9EDF",
	"䗪":"8D59",
	"䘃":"8742",
	"䘆":"99CE",
	"䘏":"8FBA",
	"䘕":"8FEB",
	"䘗":"99CF",
	"䙛":"8FC2",
	"䙺":"92C9",
	"䚀":"97DC",
	"䚡":"875D",
	"䚮":"87CC",
	"䚻":"8D45",
	"䛏":"95B3",
	"䛐":"9C79",
	"䛵":"95B2",
	"䛷":"8D4C",
	"䜓":"8FDB",
	"䜘":"9BE3",
	"䜶":"874C",
	"䝄":"874D",
	"䝎":"9E7A",
	"䝏":"8757",
	"䝼":"9BEE",
	"䞘":"99DE",
	"䞦":"FAFA",
	"䟕":"8A52",
	"䟭":"99E1",
	"䟴":"8A67",
	"䠀":"8BB5",
	"䠋":"8AAC",
	"䠷":"99E9",
	"䡝":"FBCA",
	"䡱":"97DE",
	"䢛":"95D1",
	"䢭":"99F5",
	"䢮":"FC4A",
	"䣐":"9BA9",
	"䣝":"FBDC",
	"䣭":"FE56",
	"䣳":"9EA4",
	"䣺":"9D49",
	"䤆":"95DB",
	"䤑":"89C5",
	"䤞":"99F8",
	"䤥":"9664",
	"䤪":"9055",
	"䤭":"96D4",
	"䤯":"87C4",
	"䤰":"87AE",
	"䤵":"977C",
	"䤼":"964D",
	"䤾":"97E1",
	"䥅":"9A48",
	"䥑":"9A49",
	"䥓":"FE7D",
	"䥥":"90AA",
	"䥪":"9A50",
	"䥲":"9347",
	"䦉":"8ED8",
	"䦡":"90C9",
	"䦧":"9A55",
	"䧟":"90BC",
	"䧥":"9A58",
	"䧧":"8BB8",
	"䨏":"90D5",
	"䨝":"9641",
	"䨤":"9A5A",
	"䨵":"9A5C",
	"䪖":"97C2",
	"䪤":"875C",
	"䪴":"8ABB",
	"䪸":"9BAA",
	"䫑":"90F5",
	"䫤":"9A60",
	"䫿":"9145",
	"䬐":"8C58",
	"䬙":"9A63",
	"䬠":"8C49",
	"䬬":"8BB6",
	"䬷":"FCCF",
	"䭯":"966B",
	"䭰":"9A6E",
	"䭲":"914F",
	"䭻":"9746",
	"䭾":"A0E6",
	"䮎":"92D7",
	"䮐":"9675",
	"䮓":"93D4",
	"䮖":"91BB",
	"䮗":"9679",
	"䮝":"9A70",
	"䮽":"9678",
	"䮾":"91CD",
	"䯀":"9C4A",
	"䰄":"A06F",
	"䰇":"A06A",
	"䰎":"915F",
	"䰲":"8741",
	"䰻":"9FA5",
	"䰾":"89BA",
	"䱀":"874F",
	"䱇":"874E",
	"䱗":"8755",
	"䱛":"9ECD",
	"䱭":"9A79",
	"䱷":"8CF2",
	"䱻":"8D57",
	"䱽":"9DCE",
	"䲁":"8CD2",
	"䲅":"8759",
	"䲤":"9D73",
	"䲮":"96B9",
	"䲰":"96BC",
	"䲷":"9CD1",
	"䳍":"89B7",
	"䳡":"9EEE",
	"䳢":"8749",
	"䳭":"FB43",
	"䴇":"875B",
	"䴉":"9EC9",
	"䴐":"FBD3",
	"䴴":"91AE",
	"䵶":"8D58",
	"䵷":"8746",
	"䶉":"8D56",
	"䶑":"9D78",
	"䶜":"9D7B",
	"丄":"9EB3",
	"业":"9EB2",
	"东":"9DD6",
	"両":"994F",
	"两":"89CE",
	"丨":"8BC0",
	"个":"9FC4",
	"丬":"8BD4",
	"丯":"8C72",
	"丶":"C6BF",
	"丷":"8BF9",
	"丽":"8946",
	"丿":"C6C0",
	"义":"FAE5",
	"乚":"C87B",
	"乛":"8BC6",
	"乪":"9C57",
	"乸":"9AFB",
	"亀":"89D0",
	"亁":"89CF",
	"亅":"C6C1",
	"亇":"89D1",
	"争":"89E2",
	"亘":"927E",
	"亚":"9DBA",
	"亠":"C6C2",
	"亣":"8C6F",
	"亷":"FBF8",
	"亻":"8BC7",
	"亼":"926B",
	"亿":"89D2",
	"从":"9FCF",
	"仪":"9DA9",
	"仫":"89D3",
	"仮":"99E2",
	"仸":"9267",
	"伃":"92A4",
	"众":"8C73",
	"会":"894E",
	"伨":"894F",
	"伩":"9278",
	"伲":"91B6",
	"伷":"89D4",
	"伹":"9FD2",
	"佂":"92A7",
	"佅":"95A2",
	"佋":"926E",
	"佲":"96EA",
	"侊":"926F",
	"侢":"92A3",
	"侨":"8950",
	"侫":"FA57",
	"侰":"9866",
	"侴":"8CF8",
	"侽":"89D6",
	"俈":"98B2",
	"俌":"92AB",
	"俤":"96DE",
	"俥":"92AC",
	"俰":"8C70",
	"俲":"9F6E",
	"俹":"8EF2",
	"俽":"9F6C",
	"倃":"89D8",
	"倈":"FA59",
	"倮":"92A8",
	"倴":"9163",
	"倻":"8C40",
	"偖":"9F73",
	"偘":"92AD",
	"偦":"9BE9",
	"偬":"92A9",
	"傁":"92AA",
	"傈":"89D9",
	"傐":"FD56",
	"傦":"9FA8",
	"傼":"8C71",
	"働":"92A1",
	"僐":"90E3",
	"僙":"A0A6",
	"僟":"94AB",
	"僡":"FC72",
	"僴":"97C4",
	"僼":"92AE",
	"儁":"FA67",
	"儍":"92A2",
	"儎":"FA69",
	"儫":"9268",
	"兖":"8951",
	"兠":"FA6F",
	"兪":"FA71",
	"兴":"8952",
	"兹":"945A",
	"冂":"C6C3",
	"円":"89DD",
	"冈":"C8A2",
	"冖":"C6C4",
	"冚":"9E52",
	"农":"8953",
	"冧":"9E55",
	"冨":"92BA",
	"冫":"C6C5",
	"冮":"8C5B",
	"冲":"FA7D",
	"决":"FAA8",
	"冴":"9A68",
	"况":"FA47",
	"冸":"FA7E",
	"凃":"92BB",
	"凇":"FDB6",
	"凉":"FAA2",
	"减":"FAA3",
	"凑":"FAA4",
	"凒":"9BB4",
	"凓":"FAA6",
	"凛":"89DF",
	"凟":"FDDB",
	"凢":"FAA9",
	"凤":"8954",
	"凭":"FAAB",
	"凴":"FC7A",
	"凼":"89E0",
	"凾":"9F4F",
	"刂":"C87D",
	"刅":"89E1",
	"刋":"FAB0",
	"刟":"9FCD",
	"删":"A0E7",
	"刦":"FAB1",
	"刧":"89A6",
	"刴":"9EFA",
	"刼":"FAB2",
	"剏":"87BC",
	"剗":"FAB4",
	"剙":"92C4",
	"剠":"9F6F",
	"剨":"8BB0",
	"剳":"9FAC",
	"剹":"89E3",
	"劏":"9BD3",
	"劐":"89E4",
	"劔":"FAB5",
	"劚":"9FD5",
	"务":"8955",
	"劤":"92C5",
	"动":"8956",
	"劵":"FAB3",
	"効":"FAB6",
	"勅":"FAB7",
	"勌":"9EDC",
	"勐":"FBC4",
	"勑":"9F71",
	"勠":"FABA",
	"勡":"92C7",
	"勹":"C6C6",
	"匁":"9A4C",
	"匤":"8C68",
	"匧":"89E5",
	"匬":"9F7D",
	"匲":"A0A9",
	"匳":"FAC4",
	"匸":"C6C7",
	"医":"8957",
	"卂":"FAAA",
	"华":"8958",
	"卝":"8BE3",
	"卟":"8B61",
	"卤":"9AF1",
	"卧":"9EB7",
	"卩":"C6C8",
	"卭":"FAD1",
	"却":"FAD2",
	"卽":"9EBA",
	"卾":"FAD4",
	"厓":"FAD9",
	"厠":"FADB",
	"厢":"9CE0",
	"厦":"FBF7",
	"厨":"FBFA",
	"厩":"89E7",
	"厪":"A07A",
	"厫":"FADC",
	"厮":"FADD",
	"厰":"89E9",
	"厶":"C6C9",
	"叁":"FAE2",
	"参":"89EB",
	"叅":"FAE3",
	"双":"90C8",
	"叐":"92DA",
	"发":"8959",
	"叒":"9CF5",
	"变":"895A",
	"叙":"FAE7",
	"叚":"9FA2",
	"叠":"FAEA",
	"叶":"FAED",
	"号":"8FAD",
	"叾":"FB59",
	"吓":"FAEF",
	"吔":"96EF",
	"吖":"9DEC",
	"吚":"9DCA",
	"吡":"FD6D",
	"吣":"89EC",
	"启":"FB44",
	"吲":"9DE2",
	"吴":"8C75",
	"呋":"9EC0",
	"呌":"87C5",
	"呍":"9E56",
	"呩":"9F79",
	"呪":"9AC7",
	"呭":"FAF4",
	"咅":"98A1",
	"咏":"FAF8",
	"咓":"89F0",
	"咔":"9E47",
	"咗":"9DF7",
	"咜":"9FD3",
	"咞":"9ACA",
	"咣":"89F1",
	"咤":"FAF9",
	"咲":"8E5A",
	"咴":"89F2",
	"咹":"89F3",
	"哋":"925D",
	"哌":"8B51",
	"响":"92E0",
	"哐":"89F4",
	"哚":"9FD4",
	"哣":"8A79",
	"哯":"89F5",
	"唂":"97A7",
	"唍":"93BA",
	"唓":"9E58",
	"唘":"89F6",
	"唞":"9E57",
	"唣":"89F7",
	"唥":"8A41",
	"唨":"89F8",
	"唫":"FAF1",
	"唿":"89FA",
	"啇":"FB42",
	"啉":"FABF",
	"啓":"FBA3",
	"啝":"FAF7",
	"啩":"9E4E",
	"啫":"94DC",
	"啱":"95DA",
	"啲":"9DF8",
	"啳":"9F6A",
	"啹":"8AB7",
	"喆":"FB46",
	"喐":"8A46",
	"喩":"FB47",
	"喰":"9148",
	"喴":"92DE",
	"喹":"8B53",
	"喺":"9DF6",
	"喼":"9BDA",
	"嗁":"9D7E",
	"嗗":"89FD",
	"嗘":"99E4",
	"嗞":"9E43",
	"嗪":"9DE9",
	"嗬":"8F52",
	"嗰":"9DF5",
	"嗱":"9DF0",
	"嗵":"99E7",
	"嗻":"8BBD",
	"嘅":"9DEF",
	"嘑":"9FB7",
	"嘞":"9DD0",
	"嘠":"9FEB",
	"嘡":"8DA9",
	"嘢":"9DCF",
	"嘣":"98E1",
	"嘥":"9DE5",
	"嘭":"9DC8",
	"嘷":"FB4F",
	"噃":"9DEB",
	"噍":"FB54",
	"噏":"FB55",
	"噐":"9AA2",
	"噒":"8AD6",
	"噔":"9A5F",
	"噝":"9EF5",
	"噡":"8FB7",
	"噺":"9AD2",
	"噻":"9E6A",
	"噼":"9EE8",
	"嚉":"8BBF",
	"嚊":"91C2",
	"嚋":"9D62",
	"嚒":"9260",
	"嚞":"925E",
	"嚟":"91C1",
	"嚡":"8AC5",
	"嚤":"97A3",
	"嚯":"8B6C",
	"嚱":"8D7E",
	"嚹":"9C54",
	"嚿":"9DBD",
	"囖":"9CC5",
	"团":"895B",
	"园":"FB5C",
	"囯":"FB5B",
	"囱":"FB57",
	"囻":"8765",
	"国":"98C7",
	"圀":"FB5A",
	"圕":"9CEE",
	"圝":"92E2",
	"圲":"94A7",
	"圽":"8CCC",
	"圿":"9BD4",
	"坂":"FB64",
	"坃":"FB76",
	"坆":"FB60",
	"坔":"99E5",
	"块":"9AC2",
	"坛":"91FB",
	"坟":"A073",
	"坧":"9F72",
	"坺":"9FCC",
	"坾":"98A5",
	"坿":"92E8",
	"垈":"9BBC",
	"垊":"96F3",
	"垍":"92E7",
	"垐":"FC67",
	"垜":"8B7D",
	"垡":"9BF4",
	"垧":"9EF7",
	"垪":"9EC1",
	"垳":"87C3",
	"垴":"996F",
	"垻":"96F1",
	"垾":"8E41",
	"埄":"954A",
	"埈":"97E6",
	"埗":"96F5",
	"埝":"92E6",
	"埞":"9F42",
	"埦":"FB67",
	"埯":"99A9",
	"埾":"FAE6",
	"堃":"FB69",
	"堒":"97E5",
	"堘":"87C8",
	"堢":"967D",
	"堦":"FB6C",
	"堺":"99A2",
	"塀":"9ABB",
	"塄":"9A65",
	"塇":"944E",
	"塜":"FB6E",
	"塟":"99DF",
	"塩":"98E3",
	"塬":"9254",
	"塲":"967B",
	"塳":"8AAF",
	"墒":"8C77",
	"墖":"87B0",
	"墙":"8BAF",
	"墚":"9EBD",
	"墧":"9EE6",
	"墪":"FB6F",
	"墰":"8EE1",
	"墵":"9B7D",
	"墶":"9C7E",
	"墻":"F9D9",
	"壋":"92EA",
	"壐":"8C78",
	"壜":"FB72",
	"壠":"FB71",
	"声":"895C",
	"売":"98F0",
	"壳":"96F2",
	"壻":"FB74",
	"夂":"8BC1",
	"处":"895D",
	"夅":"89DE",
	"备":"895E",
	"夊":"C6CA",
	"夑":"FE42",
	"夝":"8768",
	"够":"FB7B",
	"夲":"895F",
	"头":"8960",
	"奥":"9BCD",
	"奵":"9DD3",
	"妉":"984C",
	"妔":"9752",
	"妚":"95C3",
	"妟":"9BB6",
	"妬":"9AB9",
	"妰":"97B3",
	"妷":"9F74",
	"妸":"92F1",
	"妿":"8CFA",
	"姄":"97DF",
	"姉":"FBA6",
	"姙":"FBAB",
	"姫":"9877",
	"姯":"9854",
	"姰":"95C5",
	"姸":"9D55",
	"姹":"FBB2",
	"娂":"957E",
	"娋":"9742",
	"娍":"94E6",
	"娒":"92F5",
	"娚":"8CC5",
	"娡":"92FD",
	"娤":"FBA2",
	"娧":"9C51",
	"娪":"94E9",
	"娫":"985C",
	"娬":"92F0",
	"娽":"944C",
	"婅":"916B",
	"婔":"8B78",
	"婙":"94E2",
	"婡":"984F",
	"婣":"FBB5",
	"婨":"9271",
	"婫":"9365",
	"婮":"985B",
	"婱":"9850",
	"婹":"97BC",
	"婾":"92F3",
	"媁":"9340",
	"媂":"984D",
	"媆":"9572",
	"媈":"FDEF",
	"媑":"FDC1",
	"媖":"FBBA",
	"媙":"92EB",
	"媠":"FC73",
	"媡":"97B7",
	"媤":"876F",
	"媫":"FBB4",
	"嫃":"90A7",
	"嫎":"9741",
	"嫏":"92F4",
	"嫑":"8772",
	"嫓":"FBBC",
	"嫤":"9577",
	"嫰":"9EE2",
	"嫲":"8F78",
	"嫺":"F9DC",
	"嫾":"9672",
	"嬍":"9EB5",
	"嬑":"964B",
	"嬕":"8CAC",
	"嬟":"A0FA",
	"嬫":"9575",
	"孁":"90DA",
	"孄":"9367",
	"孆":"FEA4",
	"孊":"90DF",
	"孏":"9354",
	"学":"8961",
	"孨":"8BB4",
	"孭":"9DC0",
	"孴":"8E48",
	"孶":"FBC5",
	"孼":"FBC7",
	"宀":"C6CB",
	"宂":"FA79",
	"宐":"9E67",
	"宖":"8CD9",
	"宝":"FBD2",
	"实":"8962",
	"実":"8963",
	"宪":"FC7D",
	"宷":"8773",
	"寃":"9F6B",
	"寕":"FBCC",
	"寗":"FEAE",
	"寛":"876D",
	"寳":"FBD1",
	"寿":"FB75",
	"尅":"FBD4",
	"尓":"FBD6",
	"尔":"FBD8",
	"尜":"8B5D",
	"尞":"934C",
	"尠":"9AE2",
	"尣":"8BC9",
	"屉":"FBDB",
	"届":"9FC9",
	"屓":"9F44",
	"属":"98ED",
	"屸":"8CE9",
	"岅":"FBDD",
	"岙":"8DF2",
	"岚":"8964",
	"岜":"FDF2",
	"岞":"934D",
	"岺":"FBE7",
	"峁":"A0F2",
	"峂":"9868",
	"峑":"9F58",
	"峕":"8CE6",
	"峥":"8D73",
	"峩":"FBDE",
	"峯":"FBDF",
	"峵":"8C48",
	"峼":"8774",
	"崐":"FBE3",
	"崕":"8DA8",
	"崘":"FBE4",
	"崬":"9C75",
	"崯":"9878",
	"崾":"8D60",
	"嵆":"FBE5",
	"嵈":"8D61",
	"嵖":"8D62",
	"嵗":"A0A1",
	"嵛":"9C40",
	"嵰":"98AD",
	"嵴":"9EEA",
	"嵸":"8CEC",
	"嵻":"8CD4",
	"嶅":"9CEB",
	"嶋":"FBE0",
	"嶎":"9F51",
	"嶤":"8D65",
	"嶫":"9CF1",
	"嶶":"FC58",
	"嶹":"8D66",
	"巁":"9654",
	"巗":"FBE8",
	"巛":"C6CC",
	"巵":"9FCE",
	"帉":"FBFC",
	"帋":"9AE4",
	"帒":"9F75",
	"帮":"FBF1",
	"幂":"8D69",
	"幈":"934F",
	"幞":"934E",
	"幺":"FBF4",
	"广":"C6CE",
	"広":"FBC3",
	"庆":"8965",
	"庒":"8C7A",
	"庙":"8C7B",
	"庽":"8D6A",
	"廍":"9353",
	"廐":"9DFB",
	"廴":"FBFD",
	"廸":"9059",
	"廹":"FC40",
	"廻":"FC41",
	"廼":"FC43",
	"弌":"9361",
	"弍":"FC46",
	"弎":"9362",
	"弥":"8D6B",
	"强":"FC4C",
	"弻":"8CFE",
	"彍":"95B8",
	"彐":"C6D0",
	"彑":"8BCA",
	"彜":"987A",
	"彡":"C6D1",
	"彣":"FC51",
	"彲":"FC54",
	"彻":"FAAF",
	"徃":"8D6C",
	"徤":"FA61",
	"徧":"FC57",
	"徱":"9B70",
	"徺":"A051",
	"忂":"8C7C",
	"忄":"8BCB",
	"忛":"936E",
	"忟":"FCD5",
	"怣":"FCA9",
	"怱":"FC61",
	"总":"8966",
	"恊":"FACB",
	"恒":"F9DA",
	"恵":"937A",
	"恷":"A0E0",
	"恾":"936B",
	"悞":"FC6B",
	"悤":"A0DC",
	"悧":"9468",
	"悳":"FC6D",
	"惗":"8D71",
	"惞":"FD64",
	"惣":"99BA",
	"惧":"9AD0",
	"惨":"9A61",
	"惩":"A0E5",
	"惽":"A05B",
	"愇":"96AC",
	"愌":"9740",
	"愙":"9EF1",
	"愢":"8C4D",
	"愰":"9F7E",
	"愽":"8D72",
	"慂":"FC76",
	"慐":"96A9",
	"慙":"A06E",
	"慜":"FCAA",
	"慠":"FBCD",
	"慤":"FC74",
	"慯":"A074",
	"慽":"A071",
	"憁":"FC79",
	"憇":"FC7C",
	"憕":"9C50",
	"憘":"9379",
	"憙":"9378",
	"憜":"A0DD",
	"憷":"8D75",
	"憹":"8D76",
	"懀":"9374",
	"懏":"8D77",
	"懐":"FCA5",
	"懓":"FCA2",
	"懚":"90C3",
	"懢":"A079",
	"戬":"8D79",
	"户":"8BFC",
	"戹":"A076",
	"扌":"8BCD",
	"扨":"9F5A",
	"抂":"9FF4",
	"抅":"9FBA",
	"抐":"8D7A",
	"抝":"9E45",
	"护":"93B0",
	"抦":"A075",
	"拁":"87DD",
	"拃":"9B46",
	"担":"FCAE",
	"拕":"FCB0",
	"拟":"FA51",
	"拥":"8D7B",
	"挘":"8D7C",
	"挮":"9ED6",
	"挱":"93AC",
	"挵":"9F5B",
	"挷":"93A9",
	"捤":"A07C",
	"捬":"FCB2",
	"捹":"8AC1",
	"捿":"9FB4",
	"掋":"FCAC",
	"掹":"9E4C",
	"揁":"8FC5",
	"揑":"93AD",
	"揞":"9DC3",
	"揢":"8DA2",
	"揦":"9D4A",
	"揸":"FCB6",
	"揻":"8DA3",
	"揼":"9E4B",
	"揾":"9E4D",
	"搇":"8DA4",
	"搲":"8AFD",
	"搸":"FCB5",
	"携":"FCC3",
	"搻":"93B2",
	"摚":"8DA5",
	"摱":"93A1",
	"摼":"8AC6",
	"撍":"8A5B",
	"撑":"894D",
	"撯":"FED4",
	"撴":"8A78",
	"撶":"93AB",
	"擀":"8DA7",
	"擓":"9F45",
	"擝":"8A56",
	"擡":"FCBF",
	"擥":"FCC0",
	"擧":"8EE6",
	"擪":"8AA4",
	"攊":"8943",
	"攑":"93F3",
	"攞":"FCAB",
	"攟":"9EA2",
	"攰":"9DC7",
	"攴":"C6D2",
	"攵":"8BCE",
	"敍":"FCC5",
	"敟":"FCCB",
	"敫":"93B3",
	"敭":"FCCA",
	"斅":"FCC9",
	"斆":"8DAC",
	"斈":"FBC6",
	"斉":"8967",
	"斋":"8C7E",
	"斵":"FCCD",
	"斾":"9CF3",
	"旑":"FCD0",
	"旔":"95BB",
	"无":"FCD3",
	"旣":"FCD4",
	"旿":"8DAE",
	"昘":"FCD7",
	"昞":"93DB",
	"昣":"FE63",
	"昰":"93D5",
	"晄":"FCDA",
	"晈":"9B71",
	"晋":"FCDD",
	"晍":"8764",
	"晓":"8DAF",
	"晗":"FAF2",
	"晠":"87B5",
	"晣":"93D8",
	"晧":"FCDF",
	"晫":"93D3",
	"晳":"FCE1",
	"晽":"8E76",
	"暅":"FC62",
	"暎":"93D1",
	"暒":"8DB1",
	"暚":"9859",
	"暤":"FB52",
	"暭":"FB53",
	"暳":"FB4D",
	"暶":"9CBF",
	"暿":"9B72",
	"曍":"FB50",
	"曎":"93BE",
	"曧":"8CDB",
	"曱":"9DF1",
	"朂":"FCEB",
	"朌":"A0BB",
	"朎":"9B7E",
	"朖":"8DB3",
	"朙":"8C52",
	"朞":"9AE8",
	"朥":"8EDC",
	"朶":"9CF9",
	"杄":"FA50",
	"条":"98E7",
	"杢":"FCF3",
	"杧":"FCF2",
	"杫":"8CCA",
	"杮":"8775",
	"枂":"87BA",
	"枏":"93E5",
	"枠":"9A59",
	"枤":"8DB5",
	"枬":"FD4D",
	"枱":"FD5E",
	"枿":"8F7D",
	"柖":"9547",
	"柗":"FCF6",
	"柹":"9250",
	"柾":"8968",
	"栀":"8DB6",
	"栁":"FCFB",
	"栂":"A07D",
	"栃":"98FC",
	"栄":"8969",
	"栍":"FE4F",
	"栐":"9256",
	"栛":"FAC9",
	"栞":"93E8",
	"栢":"FCF8",
	"栶":"9CE3",
	"样":"FDA9",
	"栾":"FC44",
	"桇":"9640",
	"桊":"8DB8",
	"桕":"9B4A",
	"桖":"8FB9",
	"桝":"FCFE",
	"桥":"896A",
	"梄":"8DB9",
	"梈":"917E",
	"梘":"93F4",
	"梦":"FB7C",
	"梶":"93E7",
	"梹":"97EF",
	"梽":"FE4A",
	"棃":"FD45",
	"棅":"96A5",
	"棊":"FEE0",
	"椀":"FD48",
	"椁":"FD47",
	"椂":"FEF2",
	"椃":"FE6A",
	"椉":"8DBD",
	"椘":"9BA1",
	"椙":"8CA2",
	"椚":"9AB7",
	"椛":"8EFC",
	"椬":"9FA1",
	"椶":"FD51",
	"椾":"FAAD",
	"楃":"8DBE",
	"楆":"89A4",
	"楕":"9AD9",
	"楡":"FD4E",
	"楤":"8DC0",
	"楧":"97F0",
	"楲":"93B4",
	"楳":"FD44",
	"榀":"9FA7",
	"榅":"8DC2",
	"榊":"99B6",
	"榘":"FD52",
	"榟":"8DC1",
	"榢":"8E46",
	"榲":"A0D1",
	"槀":"9FCA",
	"槑":"92CF",
	"槕":"9CF4",
	"槖":"8DC4",
	"槡":"FD41",
	"槩":"9B4C",
	"槹":"FD57",
	"槺":"FCEF",
	"樃":"9CDE",
	"樋":"FD42",
	"樌":"986C",
	"樚":"97F9",
	"樜":"9558",
	"権":"87B6",
	"樫":"985E",
	"樬":"FE7B",
	"樭":"94CD",
	"樳":"93EE",
	"橃":"8CA3",
	"橅":"FD5A",
	"橌":"93F5",
	"橒":"93EF",
	"橓":"8EEA",
	"橗":"8F5B",
	"橣":"8C5E",
	"橥":"8DC6",
	"橱":"8DC8",
	"橴":"8DC7",
	"橺":"93F7",
	"檂":"8DC9",
	"檊":"FBF2",
	"檏":"9670",
	"檙":"8DCB",
	"檝":"FD5C",
	"檧":"8F65",
	"檫":"8DCD",
	"檱":"9DA8",
	"檲":"94F9",
	"檵":"8DCE",
	"檾":"93EA",
	"櫈":"FD5F",
	"櫉":"93F0",
	"櫊":"9FB6",
	"櫔":"8DCF",
	"櫘":"9763",
	"櫶":"8DD0",
	"欅":"93F1",
	"欝":"FD62",
	"欵":"FD65",
	"歒":"9FDB",
	"歗":"93F8",
	"歯":"8BF7",
	"歴":"FD66",
	"歺":"8BCF",
	"殁":"8DD1",
	"毁":"8DD2",
	"毜":"FD71",
	"毡":"FD6F",
	"毪":"8DD3",
	"毺":"9FE7",
	"氜":"90BD",
	"氱":"9FD0",
	"氵":"8BD0",
	"氷":"FD72",
	"氹":"9CAE",
	"氺":"8BD1",
	"氽":"8ADB",
	"汉":"FAE4",
	"汘":"95CE",
	"汚":"FD76",
	"汮":"FB62",
	"汵":"8DD4",
	"汹":"FD78",
	"汿":"8EE3",
	"沟":"9076",
	"沢":"98C6",
	"沪":"8DD5",
	"沯":"97D1",
	"沲":"9EB6",
	"泋":"FAC7",
	"泎":"A042",
	"泟":"9873",
	"泪":"9FFC",
	"泿":"8CA5",
	"洂":"8DD7",
	"洅":"92FB",
	"洆":"8DD8",
	"洤":"944F",
	"洦":"8DD9",
	"济":"896B",
	"浗":"97CE",
	"浛":"FAF3",
	"浜":"FDAE",
	"浱":"FBAF",
	"浲":"92B7",
	"涁":"8DDA",
	"涏":"9C5A",
	"涖":"FDAD",
	"涤":"8DDC",
	"涥":"9444",
	"涱":"8DDD",
	"涹":"A0D6",
	"淾":"8C41",
	"渂":"97D5",
	"渄":"944A",
	"渊":"944D",
	"渏":"97CB",
	"渕":"8DDE",
	"渘":"8DDF",
	"温":"8DE0",
	"渪":"FEF9",
	"湏":"FDC0",
	"湐":"FCF9",
	"湗":"8CDD",
	"湙":"FB7E",
	"湶":"92B3",
	"湼":"FDAF",
	"溆":"8DE1",
	"溋":"95D3",
	"溚":"89C1",
	"溵":"FD68",
	"溸":"9CB7",
	"溻":"8DE3",
	"滙":"FAC0",
	"滚":"8DE5",
	"滛":"FA64",
	"滝":"8947",
	"滢":"8DE4",
	"滨":"8DE7",
	"滩":"8DE8",
	"滺":"FDC7",
	"漄":"FDB0",
	"漋":"9445",
	"漌":"97D6",
	"漖":"FCC6",
	"漗":"9844",
	"漤":"8DE9",
	"漴":"8DEA",
	"漽":"FE50",
	"潄":"FDCC",
	"潖":"9DA7",
	"潜":"FDCD",
	"潴":"FDCF",
	"潹":"95D2",
	"澁":"8DED",
	"澊":"FCBA",
	"澝":"FDC5",
	"澟":"FDD2",
	"澵":"9CDC",
	"澻":"95CF",
	"澾":"8DEE",
	"濓":"FDD4",
	"濙":"96EC",
	"濚":"96EB",
	"濶":"90B6",
	"濸":"FDC3",
	"瀃":"98AB",
	"瀞":"96EE",
	"瀬":"8DF4",
	"灋":"FDE0",
	"灍":"8C67",
	"灐":"8DF6",
	"灔":"8DF7",
	"灜":"8FFA",
	"灧":"97D0",
	"灬":"8BD2",
	"灮":"87DE",
	"灯":"8DF8",
	"灵":"90D9",
	"灷":"8C47",
	"灹":"FAF0",
	"灾":"FDE1",
	"灿":"8DF9",
	"炁":"FDE3",
	"炉":"8DFA",
	"炋":"FB63",
	"炏":"90A6",
	"炠":"9970",
	"炣":"91EB",
	"炥":"9770",
	"炦":"986F",
	"炧":"FDE2",
	"点":"98F2",
	"炻":"9AFC",
	"炼":"896C",
	"炽":"FDFD",
	"烀":"995E",
	"烄":"95BD",
	"烌":"FDE4",
	"烐":"91E6",
	"烕":"FDE5",
	"烖":"FDE6",
	"烟":"FDE7",
	"烱":"9454",
	"烵":"99B8",
	"烾":"97E9",
	"焅":"9346",
	"焝":"9863",
	"焩":"95BC",
	"焫":"FDED",
	"焬":"FDF7",
	"焳":"9870",
	"焴":"96F6",
	"焵":"8EA9",
	"焻":"9451",
	"焾":"8E43",
	"煀":"8B5A",
	"煅":"FDEE",
	"煊":"FDF0",
	"煏":"FDF4",
	"煑":"9BF5",
	"煗":"8CEE",
	"煫":"977E",
	"煱":"9BD5",
	"煳":"9AC3",
	"煵":"97C8",
	"煶":"A0DB",
	"煷":"91D0",
	"煺":"9FE4",
	"煼":"8FDD",
	"煾":"91E9",
	"熈":"98E0",
	"熌":"92CA",
	"熎":"9857",
	"熑":"8C51",
	"熖":"FDEB",
	"熘":"9B49",
	"熢":"9D76",
	"熣":"9EAF",
	"熭":"9CCC",
	"熴":"FDEA",
	"熷":"8DF1",
	"熺":"FDFB",
	"燑":"8E53",
	"燝":"FACF",
	"燫":"96F9",
	"燵":"98BF",
	"燶":"9E49",
	"爀":"8CA7",
	"爉":"9BCA",
	"爎":"FDFE",
	"爏":"92DC",
	"爕":"FE41",
	"爖":"91CC",
	"爗":"91E2",
	"爤":"FE44",
	"爥":"875F",
	"爫":"8BD3",
	"爮":"FE47",
	"牀":"FE48",
	"牐":"9455",
	"牕":"FE4B",
	"牗":"FE4C",
	"牜":"8DBF",
	"牦":"9E78",
	"犂":"FE51",
	"犇":"9456",
	"犏":"9D61",
	"犔":"9457",
	"犟":"9966",
	"犭":"8BD5",
	"犲":"A069",
	"狍":"98B4",
	"狢":"A049",
	"猂":"A04C",
	"猄":"9E65",
	"猐":"98B5",
	"猨":"FE58",
	"猪":"9975",
	"猫":"FE53",
	"猬":"A065",
	"献":"FE59",
	"猸":"98B7",
	"猹":"98B8",
	"獁":"98BA",
	"獈":"98BB",
	"獏":"9FBC",
	"獱":"A04A",
	"獴":"9EC7",
	"玌":"8CA9",
	"玏":"98AE",
	"玘":"92D6",
	"玜":"FAE1",
	"玞":"91D4",
	"玧":"FADE",
	"玪":"FE5B",
	"玺":"8C53",
	"珄":"87BF",
	"珉":"FE5E",
	"珎":"FBD7",
	"珏":"FE5A",
	"珐":"94C5",
	"珕":"FACA",
	"珡":"98C1",
	"珢":"975C",
	"珤":"FE74",
	"珦":"9773",
	"珯":"FA46",
	"珳":"9764",
	"珷":"FE68",
	"珹":"964E",
	"珻":"9765",
	"琂":"8C5A",
	"琑":"89A1",
	"琒":"95FA",
	"琔":"92D4",
	"琕":"FE69",
	"琗":"FB45",
	"琙":"98C8",
	"琜":"90EF",
	"琞":"98C9",
	"琟":"98CA",
	"琷":"946D",
	"琸":"94B7",
	"琹":"FE6C",
	"琼":"946B",
	"瑃":"92FC",
	"瑅":"95EB",
	"瑇":"FE73",
	"瑈":"976E",
	"瑉":"FE5F",
	"瑌":"87B8",
	"瑓":"FDBD",
	"瑖":"92D5",
	"瑝":"FEB9",
	"瑠":"FE71",
	"瑡":"8778",
	"瑥":"FBBB",
	"瑨":"947A",
	"瑫":"95FB",
	"瑬":"FE77",
	"瑴":"FE79",
	"瑶":"FE75",
	"瑺":"945D",
	"璂":"FE7C",
	"璌":"9344",
	"璍":"8EA6",
	"璙":"92D3",
	"璛":"94B8",
	"璝":"8779",
	"璤":"FC71",
	"璴":"975E",
	"璹":"8CAD",
	"瓆":"87C1",
	"瓈":"FEA7",
	"瓌":"946A",
	"瓐":"93E3",
	"瓓":"98CF",
	"瓧":"A0D9",
	"瓰":"A0BF",
	"瓱":"A04D",
	"瓲":"A0B8",
	"瓸":"A0CE",
	"甅":"A0B7",
	"甎":"FEA9",
	"甙":"89C3",
	"甞":"FEAB",
	"甴":"9DF4",
	"电":"896D",
	"画":"9C7B",
	"畂":"98D2",
	"畆":"9FA9",
	"畊":"FEB2",
	"畍":"FEB1",
	"畑":"97D9",
	"畓":"A0C4",
	"畕":"9476",
	"畠":"9978",
	"畧":"FEB3",
	"畭":"98D3",
	"畮":"FEB4",
	"畲":"98D4",
	"畺":"9FB9",
	"疃":"9471",
	"疍":"98D5",
	"疎":"FEB8",
	"疒":"C6D4",
	"疞":"FEBA",
	"疱":"9E5C",
	"疴":"FEBB",
	"痃":"A044",
	"痈":"98D7",
	"痜":"98D8",
	"瘂":"FEBC",
	"瘇":"9FFE",
	"瘬":"FEBD",
	"瘻":"9DDD",
	"癀":"9EE1",
	"癍":"98DA",
	"癎":"9DDF",
	"癏":"FEBF",
	"癑":"FEBE",
	"癔":"9EEB",
	"癦":"9E59",
	"癧":"A05C",
	"癯":"FEC0",
	"癳":"9477",
	"癴":"98DC",
	"癶":"FEC1",
	"発":"98DE",
	"皐":"FEC3",
	"皡":"FEC8",
	"皥":"FEC9",
	"皷":"FECA",
	"盌":"FECB",
	"盖":"9FC2",
	"盙":"8C6B",
	"県":"98C4",
	"眎":"94B0",
	"眏":"94B1",
	"眞":"FED1",
	"眤":"A0C1",
	"眦":"FED2",
	"眫":"A0CD",
	"着":"FED3",
	"睃":"98E5",
	"睘":"FED6",
	"睲":"91E4",
	"睷":"8FC7",
	"睸":"94AE",
	"睺":"8A4F",
	"睻":"94B2",
	"瞓":"8FD4",
	"瞘":"98EA",
	"瞯":"FED8",
	"瞹":"9DE0",
	"瞾":"98EE",
	"矃":"95C4",
	"矅":"FCE8",
	"矋":"98EF",
	"矝":"8C6E",
	"矦":"FAD8",
	"矴":"FEDC",
	"矾":"A0AE",
	"砈":"9D4C",
	"砘":"98F1",
	"砜":"98F3",
	"砞":"94C1",
	"砹":"98F5",
	"砼":"FA4F",
	"砽":"96E2",
	"硂":"9450",
	"硄":"96A2",
	"硇":"98F6",
	"硋":"96E5",
	"硑":"98F7",
	"硓":"A046",
	"硔":"96E3",
	"硦":"98F8",
	"硺":"9EE4",
	"碁":"F9D6",
	"碈":"94C3",
	"碍":"94C2",
	"碯":"FEE1",
	"碱":"FEE9",
	"碶":"96E4",
	"碸":"89AC",
	"碹":"96DB",
	"磇":"FEE2",
	"磒":"94C4",
	"磓":"FEE3",
	"磗":"FEE7",
	"磘":"9FFB",
	"磤":"8C59",
	"磮":"93C9",
	"磰":"94E8",
	"磱":"FB56",
	"磵":"90C5",
	"礆":"A0A8",
	"礮":"FEE5",
	"礲":"98FD",
	"礳":"98FB",
	"礴":"FEE8",
	"礶":"8EBF",
	"礻":"8BD8",
	"礼":"FEF7",
	"祘":"8F68",
	"祙":"94C6",
	"祢":"9DEA",
	"祱":"FC69",
	"祾":"9CDA",
	"禀":"FEF3",
	"禃":"9C72",
	"禆":"FEF0",
	"禇":"89C9",
	"禑":"9941",
	"禙":"9942",
	"禝":"FEF5",
	"禟":"91D7",
	"禥":"94CC",
	"禩":"FEF8",
	"秄":"97A8",
	"秆":"FEFC",
	"秊":"8CDE",
	"秌":"FDBF",
	"秐":"87B3",
	"秔":"FEFE",
	"秢":"96D1",
	"秱":"94D5",
	"秴":"94D0",
	"稆":"9944",
	"稪":"8C63",
	"稬":"87BB",
	"稭":"A0B3",
	"稲":"87B4",
	"稺":"94CF",
	"稾":"9FFA",
	"穃":"91E5",
	"穅":"9C6A",
	"穉":"8E49",
	"穥":"8E4C",
	"穲":"87C9",
	"穽":"8E4D",
	"窃":"9A73",
	"窑":"9947",
	"窓":"8CB1",
	"窰":"8E50",
	"窻":"8E4F",
	"窼":"9949",
	"竂":"8E51",
	"竃":"8E52",
	"竈":"9AB2",
	"竉":"89A5",
	"竏":"994C",
	"竓":"9FF8",
	"竚":"8E56",
	"竛":"994D",
	"竜":"91CA",
	"竝":"8E57",
	"竢":"94E1",
	"竧":"9047",
	"竩":"8FD8",
	"竪":"8E58",
	"竼":"87A3",
	"竾":"94EB",
	"笋":"8E5C",
	"笌":"9553",
	"笔":"9FE5",
	"笟":"9F56",
	"笧":"954F",
	"笩":"8E5E",
	"笹":"996A",
	"筂":"9C64",
	"筃":"9CD9",
	"筕":"8E5D",
	"筢":"9950",
	"筬":"9951",
	"筯":"8E62",
	"筻":"9952",
	"箒":"8E68",
	"箢":"8E61",
	"箣":"9F59",
	"箮":"87D0",
	"箲":"8BB3",
	"篅":"87B9",
	"篏":"9F5D",
	"篐":"8E66",
	"篬":"8CB2",
	"篺":"8E6E",
	"篼":"9F64",
	"簒":"9953",
	"簕":"FAB8",
	"簛":"9954",
	"簵":"8E70",
	"籂":"9F61",
	"籄":"8E72",
	"籑":"A06B",
	"籖":"9F40",
	"籝":"94ED",
	"籭":"94EE",
	"籰":"9FBD",
	"籴":"8E7B",
	"类":"9957",
	"籼":"94F7",
	"籾":"9F5F",
	"粃":"8E73",
	"粆":"9F62",
	"粎":"94F6",
	"粜":"9958",
	"粦":"8E75",
	"粧":"F9DB",
	"粬":"9072",
	"粮":"94F8",
	"粸":"995A",
	"糂":"A0B0",
	"糃":"8CB3",
	"糇":"8E79",
	"糉":"8E78",
	"糍":"94F3",
	"糓":"98AF",
	"糚":"A0B2",
	"糦":"8E7A",
	"糭":"995C",
	"糳":"8E7C",
	"糵":"8E7D",
	"糹":"8BD9",
	"糼":"89A2",
	"紥":"9ED7",
	"絍":"A0B6",
	"絚":"9E42",
	"絝":"8EA4",
	"綉":"8EA7",
	"綋":"8C76",
	"綕":"8767",
	"綗":"9542",
	"綤":"987D",
	"綨":"9755",
	"綫":"8EA8",
	"綳":"8EAA",
	"緍":"89A3",
	"総":"9960",
	"緐":"9962",
	"緓":"94FC",
	"緔":"9961",
	"緜":"94FA",
	"緤":"8EAE",
	"緥":"8EB2",
	"緵":"8EB0",
	"緽":"9963",
	"緾":"97AA",
	"縇":"94FB",
	"縧":"8EBB",
	"繛":"8CDC",
	"繥":"9876",
	"繧":"8EA1",
	"繬":"8CB4",
	"繮":"8EB7",
	"繿":"9DA6",
	"纎":"9EB0",
	"纒":"8EB8",
	"纟":"9D70",
	"纤":"896E",
	"纬":"896F",
	"纺":"8970",
	"织":"8971",
	"经":"8972",
	"统":"8973",
	"缆":"8974",
	"缷":"8975",
	"罀":"8EBC",
	"罁":"8EBD",
	"罇":"8EBE",
	"罉":"9DD1",
	"罎":"94FD",
	"罒":"8BD7",
	"罓":"8BDA",
	"罱":"A0E2",
	"罸":"9FE9",
	"羏":"FDA8",
	"羓":"8AE7",
	"羗":"8EC2",
	"羣":"8EC4",
	"羮":"9964",
	"羴":"9965",
	"翝":"954E",
	"翧":"98B3",
	"翺":"8ECB",
	"耂":"8BDF",
	"耈":"8ECE",
	"耝":"8ECF",
	"耠":"9968",
	"耥":"9969",
	"耮":"996B",
	"耯":"8ED1",
	"耱":"996C",
	"耻":"8ED4",
	"耼":"8ED5",
	"联":"996D",
	"聛":"A0BE",
	"聡":"8ED6",
	"聢":"A0BC",
	"聣":"A0B5",
	"聦":"A0B4",
	"肀":"8BE0",
	"肟":"89B5",
	"肧":"8EDD",
	"肶":"9E5D",
	"肷":"9971",
	"肼":"89AE",
	"肽":"9DE8",
	"胆":"9565",
	"胩":"9972",
	"胬":"8B5C",
	"胶":"89B1",
	"脃":"A0C0",
	"脇":"8EDF",
	"脉":"9566",
	"脌":"9974",
	"脎":"9976",
	"脒":"9977",
	"脔":"9979",
	"脗":"9DDA",
	"脚":"8EE0",
	"脪":"935C",
	"脲":"9DE6",
	"脴":"8B5F",
	"脷":"9563",
	"腂":"9567",
	"腈":"9DE3",
	"腖":"997C",
	"腙":"997D",
	"腚":"997E",
	"腬":"8CFB",
	"腭":"8B5B",
	"腼":"99A3",
	"膄":"99A4",
	"膓":"99A6",
	"膥":"99A8",
	"膪":"8ABE",
	"膶":"9E61",
	"臁":"99AA",
	"臈":"A0C8",
	"臤":"99AB",
	"臯":"FEC4",
	"臶":"98C2",
	"舘":"8EE8",
	"舚":"A0BA",
	"舦":"FD77",
	"舩":"8EEE",
	"舭":"9EBF",
	"舾":"89C2",
	"艔":"99AC",
	"艢":"956B",
	"艥":"956C",
	"艶":"99AF",
	"艹":"994A",
	"艺":"8976",
	"艻":"8F48",
	"芇":"FBEE",
	"芦":"99AE",
	"芪":"8EFB",
	"芿":"8CD0",
	"苄":"8B52",
	"苊":"99B0",
	"苏":"8977",
	"苐":"8F41",
	"苘":"99B1",
	"苢":"8F49",
	"苮":"FA4D",
	"苷":"9DE4",
	"苸":"8CB5",
	"苼":"FBE9",
	"苽":"9B54",
	"苿":"99B2",
	"茋":"9E68",
	"茘":"8F4A",
	"茚":"8F42",
	"茝":"8F51",
	"茽":"9846",
	"荗":"99B4",
	"荢":"8EF5",
	"荣":"FD55",
	"荦":"9CCD",
	"药":"8978",
	"莅":"8F53",
	"莑":"8F6F",
	"莜":"8E63",
	"莬":"8F56",
	"莹":"FE76",
	"莾":"9FC6",
	"菍":"FAAC",
	"菓":"8F58",
	"菭":"9848",
	"萅":"99B7",
	"萔":"9665",
	"萖":"FA6C",
	"萘":"9DE7",
	"萜":"9E62",
	"萠":"96CC",
	"萡":"8E67",
	"萤":"FC75",
	"萦":"987E",
	"萮":"FDB9",
	"萾":"97FC",
	"葈":"98F9",
	"葊":"8F66",
	"葓":"956E",
	"葕":"9245",
	"葘":"8F60",
	"葜":"9ED1",
	"葢":"FECD",
	"葤":"99B9",
	"葱":"8F62",
	"葲":"974C",
	"葿":"91C7",
	"蒀":"955F",
	"蒄":"87AB",
	"蒈":"99BB",
	"蒒":"8E6D",
	"蒓":"8F71",
	"蒖":"94CB",
	"蒣":"95B1",
	"蒭":"9AF2",
	"蒽":"96C3",
	"蒾":"99BD",
	"蓚":"A0CF",
	"蓞":"8F6D",
	"蓡":"99BE",
	"蓢":"8EF4",
	"蓤":"8F72",
	"蓥":"95E4",
	"蓸":"99BF",
	"蔃":"9242",
	"蔄":"87D7",
	"蔅":"FBA5",
	"蔐":"99C0",
	"蔳":"FDB4",
	"蔴":"8F77",
	"蔸":"99C1",
	"蕂":"FAB9",
	"蕋":"8F40",
	"蕌":"FA44",
	"蕒":"99C2",
	"蕚":"8F5C",
	"蕟":"8CBD",
	"蕯":"99C4",
	"蕰":"99C5",
	"蕳":"8F7B",
	"薓":"8776",
	"薗":"8CB6",
	"藁":"8FA3",
	"藖":"8CCE",
	"藠":"99C6",
	"藮":"96CD",
	"藼":"96C7",
	"蘂":"8FA5",
	"蘍":"FABB",
	"蘏":"8C61",
	"蘐":"9570",
	"蘓":"87AF",
	"蘔":"9368",
	"蘖":"8F7E",
	"蘨":"8FAA",
	"蘯":"A050",
	"虂":"90D3",
	"虅":"9556",
	"虬":"8FB8",
	"虲":"99C8",
	"虾":"8FAF",
	"蚒":"99C9",
	"蚠":"9579",
	"蚭":"9F49",
	"蚲":"99CA",
	"蛯":"99CB",
	"蝰":"9DD5",
	"蝱":"8FB0",
	"蝽":"FA7A",
	"螆":"9E5F",
	"螋":"99CD",
	"螌":"A0C9",
	"螥":"9ADB",
	"螩":"A0C6",
	"螱":"8FB4",
	"蟁":"A0D7",
	"蟎":"A0C7",
	"蟖":"A043",
	"蟚":"8FB5",
	"蟮":"8FB2",
	"蟵":"A061",
	"蠄":"9E5E",
	"蠏":"8FB6",
	"蠘":"9FE8",
	"蠧":"9CB2",
	"蠭":"957C",
	"衂":"9FC7",
	"衅":"8FBB",
	"衆":"8FBC",
	"衏":"8FEC",
	"衞":"8FC0",
	"衠":"936A",
	"衤":"8BE4",
	"补":"9C7C",
	"衮":"95A1",
	"袄":"FEEC",
	"袇":"95A3",
	"袏":"8C45",
	"袐":"8CB8",
	"袜":"8FC1",
	"袝":"87B7",
	"袠":"A052",
	"袮":"99D0",
	"袴":"8FC3",
	"袵":"8FC4",
	"袿":"95A4",
	"装":"8FC6",
	"裇":"9E60",
	"裏":"F9D8",
	"裦":"95A5",
	"裵":"9CB3",
	"裿":"99D1",
	"褀":"FEF1",
	"褤":"99D2",
	"襃":"9CC2",
	"襇":"99D3",
	"襍":"95A7",
	"襔":"95A9",
	"襥":"95A6",
	"襷":"9C5D",
	"覀":"98E2",
	"覇":"8FC9",
	"覉":"A0C2",
	"覊":"8FCA",
	"覑":"99D4",
	"覔":"A0B9",
	"覥":"9B58",
	"覧":"8FCD",
	"覩":"A0D4",
	"覼":"8FCE",
	"见":"8BE5",
	"视":"8979",
	"觧":"8FD0",
	"訜":"95B6",
	"訩":"99D6",
	"訫":"95E5",
	"訸":"99D7",
	"訽":"95B5",
	"詉":"A0CA",
	"詧":"9FFD",
	"詾":"A058",
	"誐":"8FD6",
	"誔":"99D8",
	"誜":"8FD3",
	"誩":"8FE5",
	"誯":"8FE9",
	"誴":"99D9",
	"諌":"8CF7",
	"諚":"927C",
	"諪":"9C45",
	"諹":"8CE8",
	"謌":"8FDE",
	"謟":"8FDF",
	"謭":"A04B",
	"謿":"8FE2",
	"譃":"A0CC",
	"譌":"8FE3",
	"譍":"8FE4",
	"譞":"9BC4",
	"譢":"9BFC",
	"譩":"964C",
	"讁":"9AF6",
	"讃":"8CAE",
	"讏":"87CB",
	"讐":"8FE7",
	"讛":"8FE8",
	"讠":"8BE7",
	"设":"897A",
	"询":"897B",
	"豑":"99DA",
	"貛":"8FED",
	"貟":"95C0",
	"貭":"A0CB",
	"賍":"9E48",
	"賔":"99DB",
	"賖":"8FF3",
	"賛":"8FF9",
	"賩":"95C1",
	"賫":"A04E",
	"賲":"99DC",
	"賷":"A064",
	"贃":"8FF7",
	"贋":"89B0",
	"贌":"A048",
	"贑":"8FFB",
	"贒":"8FF6",
	"贘":"9DDC",
	"贜":"99DD",
	"贝":"8BE8",
	"赺":"92C1",
	"趂":"9FD6",
	"趦":"A0D2",
	"趩":"9040",
	"跀":"8AC4",
	"跃":"99E0",
	"跔":"9FF0",
	"踁":"9FF3",
	"踎":"9DBF",
	"踨":"9FF6",
	"踪":"95C8",
	"踭":"9E5A",
	"踺":"99E3",
	"蹆":"8A4A",
	"蹏":"9FF1",
	"蹨":"8AA7",
	"蹱":"99E6",
	"蹵":"9FF7",
	"蹷":"9FED",
	"蹾":"8A5C",
	"躀":"9DAE",
	"躧":"95C9",
	"躭":"9048",
	"躰":"99E8",
	"躶":"9049",
	"躹":"8CBA",
	"躼":"90B1",
	"軃":"904A",
	"軎":"99EA",
	"軚":"9BD1",
	"転":"99EB",
	"軤":"99EC",
	"軭":"99ED",
	"軲":"99EE",
	"輙":"904C",
	"輭":"904D",
	"輰":"95CB",
	"轁":"97E2",
	"轊":"95CC",
	"轜":"9F78",
	"车":"897C",
	"轧":"897D",
	"轮":"897E",
	"输":"995D",
	"辠":"9B5A",
	"辥":"9050",
	"辧":"8C4F",
	"辳":"9054",
	"辵":"C6D6",
	"辶":"9AA8",
	"辷":"99EF",
	"辸":"FEEB",
	"边":"9DA3",
	"辺":"9DA1",
	"辻":"9943",
	"込":"9945",
	"达":"9D7D",
	"迁":"99F0",
	"迊":"99F1",
	"迌":"99F2",
	"迏":"8CBC",
	"运":"9D60",
	"迚":"A0A3",
	"迹":"905B",
	"逈":"9EDB",
	"递":"9D79",
	"逳":"99F3",
	"逷":"9062",
	"遆":"87BD",
	"遌":"9F55",
	"遖":"9BF9",
	"遡":"9065",
	"遤":"96E0",
	"遬":"98BE",
	"邨":"9068",
	"邮":"906C",
	"邻":"95D8",
	"郄":"906A",
	"酑":"9FB2",
	"酙":"9FAE",
	"酜":"9FB0",
	"酞":"89AD",
	"酧":"906E",
	"酰":"9E71",
	"酶":"9E4A",
	"酼":"9FDC",
	"醌":"89AB",
	"醎":"9FB8",
	"醩":"9070",
	"醶":"8B63",
	"醻":"95DC",
	"釄":"9071",
	"釖":"FC5E",
	"釟":"8949",
	"釥":"965B",
	"釶":"8C50",
	"釺":"94A6",
	"釾":"8FD5",
	"鈈":"9E73",
	"鈎":"9075",
	"鈓":"99F7",
	"鈘":"87B2",
	"鈡":"8CBF",
	"鈨":"99F9",
	"鈪":"9663",
	"鈫":"95B9",
	"鈵":"94D4",
	"鈼":"FCFA",
	"鉁":"9077",
	"鉄":"90AB",
	"鉕":"9D4D",
	"鉘":"99FA",
	"鉝":"92E3",
	"鉟":"97BB",
	"鉢":"9078",
	"鉫":"99FB",
	"鉮":"97E0",
	"鉷":"96DC",
	"銁":"9CA8",
	"銄":"9772",
	"銉":"9440",
	"銏":"92F2",
	"銮":"99FD",
	"銱":"99FC",
	"銹":"F9D7",
	"銺":"964A",
	"銾":"96D8",
	"銿":"99FE",
	"鋔":"904B",
	"鋛":"FA41",
	"鋣":"9A40",
	"鋥":"975B",
	"鋫":"9A41",
	"鋬":"91DD",
	"鋲":"93FC",
	"鋳":"9A42",
	"鋴":"9A43",
	"鋶":"9659",
	"鋽":"9A44",
	"錃":"9051",
	"錇":"94BF",
	"錬":"90A2",
	"錰":"9CAB",
	"錱":"9776",
	"鍀":"FC55",
	"鍁":"FE45",
	"鍂":"94A8",
	"鍃":"9A45",
	"鍄":"FA4B",
	"鍅":"9DE1",
	"鍈":"96D9",
	"鍟":"9774",
	"鍢":"FDF5",
	"鍦":"92E5",
	"鍨":"9645",
	"鍩":"91DA",
	"鍫":"90A3",
	"鍮":"A05F",
	"鍳":"90AF",
	"鍴":"97BF",
	"鍸":"914C",
	"鍽":"967A",
	"鎁":"91DE",
	"鎄":"9A46",
	"鎅":"FEB0",
	"鎆":"9779",
	"鎇":"946C",
	"鎐":"9858",
	"鎜":"9266",
	"鎠":"93FB",
	"鎭":"9A47",
	"鎸":"9749",
	"鎻":"9748",
	"鎽":"934A",
	"鎿":"9CE2",
	"鏆":"9264",
	"鏋":"91DF",
	"鏓":"FB79",
	"鏛":"96D7",
	"鏠":"9343",
	"鏰":"FDCB",
	"鏱":"FE7A",
	"鏳":"91DB",
	"鏴":"8C6A",
	"鐁":"97AF",
	"鐄":"95DD",
	"鐈":"9348",
	"鐗":"9A4B",
	"鐛":"FC45",
	"鐝":"9A4D",
	"鐤":"91BC",
	"鐥":"90E2",
	"鐦":"90B4",
	"鐧":"95E1",
	"鐭":"9A4E",
	"鐯":"87AD",
	"鐾":"9A4F",
	"鑂":"FE40",
	"鑃":"FE43",
	"鑍":"96DD",
	"鑔":"9A51",
	"鑘":"96A7",
	"鑛":"90B0",
	"鑥":"9C4E",
	"鑧":"9443",
	"鑬":"8EBA",
	"鑹":"9A52",
	"鑻":"FCC1",
	"钅":"8BE9",
	"钟":"9CAF",
	"钢":"8BFD",
	"铁":"9ABC",
	"铃":"9AB8",
	"铜":"9AAE",
	"银":"9AA7",
	"锭":"9A53",
	"镇":"9D74",
	"镸":"8BEA",
	"长":"8BEB",
	"閅":"90B2",
	"閖":"95E9",
	"閗":"95E8",
	"閙":"95E6",
	"閠":"90B5",
	"関":"9A54",
	"閦":"90B3",
	"閧":"95E7",
	"閪":"8B50",
	"门":"8BEC",
	"间":"9A56",
	"阝":"8BFB",
	"阳":"9A57",
	"阸":"A0AA",
	"陁":"9FA6",
	"际":"99CC",
	"陖":"9C59",
	"险":"99B5",
	"陻":"90BE",
	"隁":"9FAF",
	"随":"95F2",
	"隖":"90BF",
	"隣":"90C1",
	"隥":"FEE4",
	"隶":"90C4",
	"隽":"90C7",
	"雴":"92E4",
	"霃":"9F52",
	"霛":"90DB",
	"霡":"A066",
	"霱":"90D2",
	"霴":"876B",
	"霶":"90D4",
	"靀":"9A5B",
	"靁":"95FD",
	"靊":"87B1",
	"靑":"8BC4",
	"靕":"8C66",
	"靗":"90DE",
	"靝":"9CE4",
	"靟":"90E1",
	"靭":"9E46",
	"靱":"9651",
	"鞇":"FB58",
	"鞉":"90E6",
	"鞛":"9650",
	"鞟":"90E7",
	"鞱":"90E8",
	"鞲":"9A5D",
	"鞴":"9F7A",
	"鞸":"9B5C",
	"鞺":"9F7C",
	"鞽":"FC52",
	"鞾":"90E9",
	"韀":"90EA",
	"韂":"9A5E",
	"韈":"9F76",
	"韒":"90EB",
	"韠":"90EC",
	"韦":"8BEE",
	"韮":"90EE",
	"韲":"91C6",
	"韵":"90F2",
	"頔":"FCBC",
	"頕":"8A74",
	"頟":"9657",
	"頣":"9CEF",
	"頮":"9FDF",
	"頳":"90F7",
	"頴":"90F6",
	"顇":"9B5E",
	"顋":"90F8",
	"顖":"8CFC",
	"顦":"90F9",
	"顨":"8CC9",
	"顬":"FA6A",
	"页":"8BEF",
	"颴":"9FE0",
	"颷":"9142",
	"颹":"9A62",
	"飃":"9569",
	"飇":"9144",
	"飈":"9143",
	"飊":"9141",
	"风":"8BF0",
	"飜":"9660",
	"飞":"8BF1",
	"飠":"99F6",
	"飡":"9149",
	"飦":"914A",
	"飬":"914B",
	"飱":"9A64",
	"飵":"8ABF",
	"餎":"9A66",
	"餙":"9A67",
	"餜":"9A69",
	"餷":"9A6A",
	"餸":"9652",
	"餹":"914D",
	"餻":"9666",
	"饀":"9F7B",
	"饂":"9A6B",
	"饊":"A06C",
	"饍":"9667",
	"饝":"9A6C",
	"饢":"9A6D",
	"饣":"8BF2",
	"馛":"966A",
	"馤":"FCEA",
	"馪":"966C",
	"馸":"91C4",
	"馼":"9677",
	"駄":"99F4",
	"駅":"9A6F",
	"駚":"9FAB",
	"駠":"8CBE",
	"駡":"8EC1",
	"駦":"9555",
	"駵":"9152",
	"騌":"9153",
	"騐":"9155",
	"騟":"955D",
	"騡":"9671",
	"騦":"9C6D",
	"騯":"9673",
	"騻":"9154",
	"騼":"9A71",
	"驘":"9156",
	"驜":"966D",
	"驣":"9557",
	"马":"89C6",
	"骏":"89C7",
	"骲":"8A6A",
	"骶":"8B57",
	"骺":"9FE1",
	"骽":"9B5F",
	"髗":"A05D",
	"髠":"915B",
	"髢":"915C",
	"髴":"915E",
	"髿":"9F5C",
	"鬂":"9F57",
	"鬉":"9F65",
	"鬏":"9A72",
	"鬔":"9160",
	"鬪":"9F5E",
	"鬭":"9161",
	"鬴":"9164",
	"鬹":"9F41",
	"魀":"9169",
	"魐":"9168",
	"魩":"9A74",
	"魿":"96B2",
	"鮁":"9A75",
	"鮃":"FDA5",
	"鮋":"9EE9",
	"鮍":"8BBA",
	"鮎":"916D",
	"鮏":"A060",
	"鮗":"9FDE",
	"鮝":"9FC3",
	"鮟":"96B5",
	"鮰":"A067",
	"鯏":"96B3",
	"鯝":"9A76",
	"鯩":"95D5",
	"鯭":"9ECA",
	"鯱":"9A77",
	"鯴":"9A78",
	"鯿":"9170",
	"鰂":"916F",
	"鰊":"9FA3",
	"鰌":"9171",
	"鰐":"96B1",
	"鰕":"9F63",
	"鰛":"9F67",
	"鰟":"8BB9",
	"鰠":"9A7A",
	"鰦":"8B56",
	"鰯":"9ADA",
	"鰵":"96B0",
	"鰺":"9A7E",
	"鱅":"9DDE",
	"鱏":"96AD",
	"鱓":"96AE",
	"鱝":"9EA1",
	"鱲":"9E50",
	"鱻":"96AF",
	"鱼":"8BF4",
	"鴂":"9FA4",
	"鴌":"96BD",
	"鴖":"96F4",
	"鴡":"96B8",
	"鴴":"FAA1",
	"鴹":"91A7",
	"鵄":"A05E",
	"鵉":"9A7D",
	"鵎":"8948",
	"鵐":"9EB1",
	"鵞":"9DDB",
	"鵭":"95BF",
	"鵮":"8A73",
	"鵼":"9EFE",
	"鵾":"917A",
	"鶃":"917B",
	"鶓":"9AA3",
	"鶥":"96C2",
	"鶫":"9F77",
	"鶽":"9AA4",
	"鷀":"9AA5",
	"鷄":"91A1",
	"鷉":"89B8",
	"鷔":"9173",
	"鷼":"9AA6",
	"鸊":"89BD",
	"鸌":"89B9",
	"鸎":"917D",
	"鸘":"96BB",
	"鸜":"9FF2",
	"鸟":"8BF5",
	"鹻":"9AA9",
	"麁":"9F54",
	"麄":"9FE3",
	"麅":"9EED",
	"麐":"91AA",
	"麕":"91AB",
	"麖":"A070",
	"麘":"9F6D",
	"麞":"91AC",
	"麢":"91AD",
	"麦":"A0FD",
	"麨":"9FE2",
	"麪":"91AF",
	"麫":"9E41",
	"麬":"9AAA",
	"麯":"91B0",
	"麱":"9AAB",
	"麽":"9AAC",
	"麿":"9A4A",
	"黁":"91B2",
	"黄":"8BF6",
	"黆":"9AAD",
	"黇":"89B6",
	"黢":"9AAF",
	"黱":"9AB0",
	"黸":"9AB1",
	"黾":"9AA1",
	"鼂":"91B9",
	"鼈":"91BA",
	"鼗":"91BE",
	"鼦":"A041",
	"鼧":"8BB7",
	"鼹":"91C0",
	"齄":"9AB3",
	"齅":"91C3",
	"齐":"A0FC",
	"齓":"9FEE",
	"齚":"9F69",
	"齢":"91C8",
	"齩":"91C9",
	"齿":"8DE6",
	"龎":"91CB",
	"龖":"87AC",
	"龗":"87A4",
	"龙":"89C8",
	"龟":"8DAA",
	"龥":"9FDD",
	"龦":"8C43",
	"龧":"8C6D",
	"龨":"8C74",
	"龩":"8CB7",
	"龪":"8CB9",
	"龫":"8CBB",
	"龬":"8CC0",
	"龭":"8CD7",
	"龮":"8CD8",
	"龯":"8CDA",
	"龰":"C8A1",
	"龱":"C8A3",
	"龲":"8CED",
	"龳":"8D48",
	"鿇":"87C2",
	"鿈":"87D2",
	"鿉":"87D6",
	"鿊":"87DA",
	"鿋":"87DF",
	"龜":"8BF8",
	"𠀡":"9C71",
	"𠀾":"9375",
	"𠁆":"9376",
	"𠁎":"9548",
	"𠁨":"8EC6",
	"𠂆":"8BC5",
	"𠂇":"8BFA",
	"𠂊":"C87C",
	"𠂔":"9AB4",
	"𠃊":"884E",
	"𠃋":"884B",
	"𠃌":"C87A",
	"𠃍":"8848",
	"𠃑":"8847",
	"𠃮":"A0F6",
	"𠄌":"8845",
	"𠄎":"8853",
	"𠄘":"FCAD",
	"𠆤":"8CF5",
	"𠆩":"8AAD",
	"𠆫":"9272",
	"𠇁":"FC47",
	"𠇔":"94DF",
	"𠇲":"9FD1",
	"𠈄":"FBCB",
	"𠈌":"927D",
	"𠈔":"98A4",
	"𠈹":"8CF9",
	"𠉛":"94E7",
	"𠉴":"90CB",
	"𠉵":"927B",
	"𠊙":"94D8",
	"𠊞":"FC5F",
	"𠊠":"FA54",
	"𠊷":"9AB5",
	"𠊿":"96DA",
	"𠋀":"9279",
	"𠋥":"FA74",
	"𠌊":"9275",
	"𠌥":"8DFB",
	"𠍁":"8A49",
	"𠍅":"92DF",
	"𠍆":"9B7C",
	"𠍇":"FA63",
	"𠍾":"FA60",
	"𠍿":"926D",
	"𠎀":"FA62",
	"𠎠":"9AB6",
	"𠎧":"976B",
	"𠎵":"FD6A",
	"𠏉":"FD54",
	"𠏋":"9273",
	"𠏵":"97D8",
	"𠏼":"9FBB",
	"𠐓":"9342",
	"𠐔":"9276",
	"𠐟":"FA65",
	"𠑥":"926C",
	"𠒇":"FA6E",
	"𠒎":"9EE0",
	"𠒑":"92C0",
	"𠒒":"92BF",
	"𠒣":"92BE",
	"𠓗":"9ABA",
	"𠓼":"8AB3",
	"𠓾":"9775",
	"𠕇":"FA40",
	"𠖎":"FA76",
	"𠖥":"FBD0",
	"𠖳":"FA7B",
	"𠗃":"FE6D",
	"𠗊":"9BB3",
	"𠗐":"89CC",
	"𠗕":"9ABE",
	"𠗟":"FA42",
	"𠗠":"92BC",
	"𠗫":"945C",
	"𠘑":"9BB5",
	"𠘕":"9ABF",
	"𠘙":"98A7",
	"𠘚":"97A4",
	"𠘰":"90FD",
	"𠙖":"FC7B",
	"𠙶":"9AC0",
	"𠜎":"92C3",
	"𠜱":"8AAA",
	"𠝹":"9BD0",
	"𠠬":"9550",
	"𠡳":"92C6",
	"𠣕":"98A6",
	"𠤖":"9546",
	"𠤣":"FD63",
	"𠥔":"FAC2",
	"𠥹":"9EC3",
	"𠧧":"89B2",
	"𠨑":"9C66",
	"𠩐":"9053",
	"𠩯":"8C62",
	"𠪊":"87A8",
	"𠪴":"97C1",
	"𠫂":"9AC4",
	"𠫍":"9AC5",
	"𠬍":"8EEF",
	"𠮏":"FAE9",
	"𠮟":"8D40",
	"𠮨":"9262",
	"𠮩":"8AF7",
	"𠮿":"9AC6",
	"𠯆":"92E1",
	"𠯋":"9AC9",
	"𠯢":"FAC6",
	"𠯫":"97A5",
	"𠯻":"9ACB",
	"𠯿":"FA72",
	"𠰋":"8A5E",
	"𠰍":"94E0",
	"𠰠":"92CC",
	"𠰴":"8AE5",
	"𠰺":"FE5C",
	"𠰻":"9ACC",
	"𠱁":"9DF9",
	"𠱂":"8A43",
	"𠱃":"8AA6",
	"𠱓":"9ACD",
	"𠱥":"9ACE",
	"𠱷":"FAEE",
	"𠱸":"9BCC",
	"𠱼":"9ACF",
	"𠲍":"9AD1",
	"𠲖":"9DFA",
	"𠲜":"9D7C",
	"𠲵":"9AD3",
	"𠲸":"97A6",
	"𠳏":"995F",
	"𠳓":"FBF6",
	"𠳔":"9FC5",
	"𠳕":"8A59",
	"𠳖":"8B6B",
	"𠳝":"9AD4",
	"𠳭":"9AD5",
	"𠳿":"97A2",
	"𠴕":"8A44",
	"𠴨":"9F4A",
	"𠴱":"90A1",
	"𠴲":"FDA4",
	"𠵆":"8A64",
	"𠵇":"8AF2",
	"𠵈":"8AF8",
	"𠵉":"9DD8",
	"𠵌":"94D6",
	"𠵍":"FAFE",
	"𠵎":"FBA7",
	"𠵯":"9AD6",
	"𠵱":"9F4D",
	"𠵴":"FAF6",
	"𠵼":"8A57",
	"𠵾":"8B43",
	"𠵿":"8B44",
	"𠶖":"8AB6",
	"𠶜":"8AC0",
	"𠶧":"9E54",
	"𠶲":"9AD7",
	"𠷈":"9AD8",
	"𠸄":"9ADC",
	"𠸉":"8ACA",
	"𠸊":"9EA8",
	"𠸍":"9263",
	"𠸎":"9ADD",
	"𠸏":"8B65",
	"𠸐":"8B6F",
	"𠸑":"8B7E",
	"𠸖":"8F43",
	"𠸝":"92D0",
	"𠹌":"8AF4",
	"𠹭":"9DBE",
	"𠹳":"9AE1",
	"𠹵":"FCDE",
	"𠹶":"9DFD",
	"𠹷":"8B66",
	"𠹸":"8B70",
	"𠹹":"8B75",
	"𠹺":"8AE4",
	"𠹻":"8BA4",
	"𠺌":"8AED",
	"𠺖":"8A5D",
	"𠺘":"8B48",
	"𠺝":"9DED",
	"𠺢":"9E40",
	"𠺪":"8AEF",
	"𠺫":"8AF6",
	"𠺬":"9E76",
	"𠺶":"9EE3",
	"𠻗":"9ADE",
	"𠻘":"8DFE",
	"𠻝":"FAFC",
	"𠻸":"9CB1",
	"𠻹":"9E77",
	"𠻺":"8B64",
	"𠻻":"8B67",
	"𠼝":"974B",
	"𠼦":"9653",
	"𠼭":"9AE0",
	"𠼮":"8B4A",
	"𠼰":"8AF1",
	"𠼱":"8AD7",
	"𠼻":"A0AB",
	"𠽌":"8AB5",
	"𠽤":"8A5F",
	"𠾍":"8AEE",
	"𠾐":"9ADF",
	"𠾭":"8AFE",
	"𠾴":"8A58",
	"𠾵":"8BA3",
	"𠾶":"8BA7",
	"𠾼":"9AE3",
	"𠿟":"9261",
	"𠿪":"9DD7",
	"𠿫":"9E7D",
	"𠿬":"9EA7",
	"𠿭":"9EAB",
	"𡀔":"9042",
	"𡀝":"8B79",
	"𡀞":"8B7A",
	"𡁏":"9AE6",
	"𡁜":"9AE5",
	"𡁯":"8A7E",
	"𡁵":"9E44",
	"𡁶":"9AE7",
	"𡁷":"8A7C",
	"𡁸":"8B71",
	"𡁻":"9AE9",
	"𡂈":"9AEA",
	"𡂖":"9AEB",
	"𡂝":"8ABD",
	"𡂴":"FB4E",
	"𡂿":"9AED",
	"𡃀":"8AF9",
	"𡃁":"9E63",
	"𡃇":"8B49",
	"𡃈":"8ACE",
	"𡃉":"8B6E",
	"𡃏":"8AE8",
	"𡃓":"9AEE",
	"𡃤":"92CE",
	"𡃴":"8A5A",
	"𡃵":"8B7B",
	"𡃶":"8B7C",
	"𡄯":"9AEF",
	"𡄻":"9AF0",
	"𡄽":"8AFA",
	"𡅅":"8941",
	"𡅈":"8B72",
	"𡅏":"8AF3",
	"𡆀":"8BA8",
	"𡆇":"9EAE",
	"𡇙":"9E72",
	"𡈼":"FB73",
	"𡉏":"FB5F",
	"𡉼":"90BA",
	"𡊨":"91FE",
	"𡊩":"9EF6",
	"𡊰":"97ED",
	"𡋣":"9AF3",
	"𡋾":"A0EE",
	"𡌂":"967C",
	"𡌃":"9345",
	"𡌄":"986E",
	"𡌅":"FA56",
	"𡌶":"9AF5",
	"𡌺":"FC4B",
	"𡍵":"9AF4",
	"𡍶":"FEDE",
	"𡎎":"FCB7",
	"𡎘":"97F1",
	"𡎜":"97C7",
	"𡏅":"9CCB",
	"𡏆":"9240",
	"𡏭":"9CE8",
	"𡏾":"91FD",
	"𡐓":"974E",
	"𡐖":"FB68",
	"𡐤":"976C",
	"𡐿":"8CC2",
	"𡑒":"97E8",
	"𡑔":"FB6A",
	"𡑕":"8B74",
	"𡒊":"8EE7",
	"𡒗":"FDC8",
	"𡒶":"9241",
	"𡓨":"96A1",
	"𡓽":"8EF3",
	"𡕷":"9AF7",
	"𡖂":"8FA6",
	"𡖖":"FAD6",
	"𡘊":"9CC7",
	"𡘓":"FAD7",
	"𡘙":"9AF8",
	"𡘾":"FBA1",
	"𡙡":"8EC5",
	"𡚒":"FBA4",
	"𡚸":"FBC2",
	"𡚺":"9AC1",
	"𡛀":"91FA",
	"𡛁":"FEDB",
	"𡛂":"97AB",
	"𡛓":"9147",
	"𡛕":"FBB1",
	"𡛟":"8FEA",
	"𡛦":"94D2",
	"𡛧":"FE61",
	"𡛨":"FACE",
	"𡛺":"92ED",
	"𡛻":"91F3",
	"𡛼":"93C6",
	"𡛾":"935A",
	"𡜍":"FAFB",
	"𡜐":"92EF",
	"𡜦":"FAC8",
	"𡜺":"9847",
	"𡜻":"9366",
	"𡜼":"9855",
	"𡝗":"96E6",
	"𡝬":"9F43",
	"𡝭":"9FAA",
	"𡝮":"94DA",
	"𡝯":"92EE",
	"𡝰":"FCAF",
	"𡝱":"FBFB",
	"𡝳":"8EF9",
	"𡝴":"91F6",
	"𡞫":"9364",
	"𡞰":"94F5",
	"𡞱":"9CB6",
	"𡞲":"FBAD",
	"𡞳":"984E",
	"𡞴":"8F44",
	"𡞵":"96FD",
	"𡟃":"9AF9",
	"𡟇":"9AFA",
	"𡟙":"9769",
	"𡟚":"95D4",
	"𡟛":"984B",
	"𡟜":"FBAA",
	"𡟟":"987C",
	"𡟯":"91EA",
	"𡟵":"9DAF",
	"𡟶":"9DC5",
	"𡟸":"91F1",
	"𡟹":"8EB1",
	"𡟺":"97A9",
	"𡟻":"FBAC",
	"𡟼":"FCB8",
	"𡠠":"9CB9",
	"𡠨":"FBB0",
	"𡠩":"FCD2",
	"𡠪":"93CB",
	"𡠭":"9AFD",
	"𡠹":"91F4",
	"𡠺":"8BAC",
	"𡠻":"A055",
	"𡡀":"9574",
	"𡡅":"95BE",
	"𡡒":"97AD",
	"𡡞":"8EE9",
	"𡡡":"92F8",
	"𡡢":"97BE",
	"𡡣":"916C",
	"𡡤":"94AA",
	"𡡷":"FC63",
	"𡡻":"9DC6",
	"𡢃":"97B5",
	"𡢄":"92B8",
	"𡢅":"91EF",
	"𡢞":"FEA6",
	"𡢟":"9760",
	"𡢠":"9358",
	"𡢡":"9576",
	"𡢢":"8FAC",
	"𡢾":"91EC",
	"𡢿":"97B4",
	"𡣑":"91F7",
	"𡣖":"974A",
	"𡣗":"FB49",
	"𡣘":"9578",
	"𡣙":"93BC",
	"𡣺":"91D6",
	"𡤃":"9355",
	"𡤄":"9356",
	"𡤅":"9851",
	"𡤐":"8FF8",
	"𡤑":"FBC0",
	"𡤒":"93F2",
	"𡤕":"90D0",
	"𡤜":"9C44",
	"𡤢":"9255",
	"𡤧":"9363",
	"𡤻":"91A5",
	"𡥄":"A0ED",
	"𡥘":"FD6B",
	"𡥪":"9AFE",
	"𡥼":"9351",
	"𡦀":"8C57",
	"𡦃":"FA78",
	"𡦈":"FEA8",
	"𡦖":"9350",
	"𡧛":"FA4C",
	"𡧳":"92F7",
	"𡨭":"9B40",
	"𡨴":"FBCE",
	"𡩅":"9B41",
	"𡩋":"FEAD",
	"𡩣":"8761",
	"𡭄":"FBD5",
	"𡯁":"8BC2",
	"𡯂":"9A7C",
	"𡰪":"9B42",
	"𡱰":"9B43",
	"𡲢":"9E79",
	"𡲥":"FBD9",
	"𡲬":"9B44",
	"𡵆":"A0A7",
	"𡵓":"877B",
	"𡵞":"876E",
	"𡶐":"9BF3",
	"𡶶":"8C79",
	"𡶺":"935E",
	"𡷊":"89CB",
	"𡷑":"9F53",
	"𡷫":"93D7",
	"𡷹":"FBE1",
	"𡸜":"FED0",
	"𡸣":"8CF1",
	"𡸷":"FBE2",
	"𡸽":"FCE3",
	"𡺉":"9074",
	"𡺤":"FBE6",
	"𡺨":"9BB7",
	"𡻈":"9B45",
	"𡻕":"9B47",
	"𡼏":"9F50",
	"𡼕":"9B48",
	"𡽪":"FC5B",
	"𡾞":"98A9",
	"𡾡":"9CFD",
	"𡿨":"884C",
	"𢁅":"9B4B",
	"𢁉":"FBEC",
	"𢁾":"8C69",
	"𢂚":"9BA8",
	"𢃇":"8AD5",
	"𢃼":"FA73",
	"𢄪":"FD59",
	"𢅛":"91A2",
	"𢅳":"FBED",
	"𢅺":"9CA9",
	"𢆡":"8AA8",
	"𢇁":"8D42",
	"𢇃":"9BC3",
	"𢈈":"8AE1",
	"𢉼":"9B4E",
	"𢌡":"95D0",
	"𢌥":"905F",
	"𢎽":"97EE",
	"𢏐":"FC4E",
	"𢏗":"9B4F",
	"𢏺":"9B50",
	"𢑥":"9EC6",
	"𢑱":"FC50",
	"𢒋":"FD73",
	"𢒑":"FDA7",
	"𢒰":"9DA2",
	"𢒼":"87D1",
	"𢓁":"87D3",
	"𢓉":"87D4",
	"𢓌":"87D5",
	"𢓭":"FA58",
	"𢔓":"FA5E",
	"𢔛":"A059",
	"𢔰":"FA75",
	"𢕔":"FBBE",
	"𢖍":"9CA2",
	"𢖯":"9370",
	"𢖾":"9371",
	"𢘛":"9377",
	"𢘜":"FEEF",
	"𢘫":"936D",
	"𢙨":"FC5D",
	"𢙺":"90B8",
	"𢚖":"8AFC",
	"𢚘":"FB41",
	"𢛴":"9E6B",
	"𢛵":"94E3",
	"𢛶":"8EE2",
	"𢜒":"8C7D",
	"𢜔":"8ED7",
	"𢜛":"9C4D",
	"𢜟":"96A3",
	"𢜪":"9B51",
	"𢝵":"8AC3",
	"𢞁":"96AA",
	"𢞖":"8CE2",
	"𢞴":"FC68",
	"𢞵":"8B6D",
	"𢟍":"FD67",
	"𢠃":"8AE9",
	"𢡟":"FCA1",
	"𢡠":"936C",
	"𢡱":"9B52",
	"𢢭":"FE70",
	"𢣁":"FCA8",
	"𢣷":"FCE9",
	"𢤦":"9CB4",
	"𢤹":"8AEA",
	"𢥏":"9B53",
	"𢥧":"9B55",
	"𢥫":"96AB",
	"𢦀":"FCA7",
	"𢦓":"9B56",
	"𢩦":"8ABC",
	"𢫏":"8ACB",
	"𢫕":"9B57",
	"𢫦":"89CD",
	"𢫨":"9B59",
	"𢬎":"9B5B",
	"𢬢":"93A5",
	"𢬿":"9B5D",
	"𢭃":"9E4F",
	"𢭪":"93A3",
	"𢯊":"8A7B",
	"𢯎":"8B42",
	"𢰦":"9750",
	"𢰧":"8FB3",
	"𢰸":"8A50",
	"𢱌":"9B60",
	"𢱑":"8B45",
	"𢱕":"8B46",
	"𢱢":"9DFE",
	"𢲈":"9B62",
	"𢲛":"937B",
	"𢲡":"93B1",
	"𢲩":"8A60",
	"𢲲":"8AD8",
	"𢲷":"9B63",
	"𢳂":"8A69",
	"𢳆":"8A47",
	"𢳉":"8ACC",
	"𢴇":"937C",
	"𢴈":"9B65",
	"𢴒":"9B66",
	"𢵄":"8A72",
	"𢵌":"8A7A",
	"𢵧":"93AF",
	"𢶍":"8AB0",
	"𢶕":"9B68",
	"𢶠":"9EA3",
	"𢶣":"FAEC",
	"𢶤":"8B77",
	"𢶷":"9B67",
	"𢷮":"8B59",
	"𢸍":"FCB1",
	"𢸶":"FCBB",
	"𢹂":"9B69",
	"𢹸":"93A8",
	"𢺋":"8AE0",
	"𢺳":"9E51",
	"𢻯":"8F5F",
	"𢽴":"9B6A",
	"𢿌":"9B6B",
	"𢿣":"97EC",
	"𣀳":"9B6C",
	"𣁄":"FE4E",
	"𣁋":"FDC2",
	"𣁦":"9B6D",
	"𣁽":"9167",
	"𣁾":"FCCC",
	"𣂎":"93B6",
	"𣂷":"90E4",
	"𣂼":"90E5",
	"𣃚":"9EF2",
	"𣄃":"93CA",
	"𣄽":"8BBC",
	"𣅽":"8F46",
	"𣆂":"93CF",
	"𣆤":"FCDB",
	"𣆥":"FCDC",
	"𣆳":"93C0",
	"𣇈":"FCE6",
	"𣇉":"96E7",
	"𣇪":"87A7",
	"𣇷":"FCD8",
	"𣇸":"FCD9",
	"𣇹":"FDA6",
	"𣈏":"93CE",
	"𣈥":"95F1",
	"𣈯":"9CE9",
	"𣈱":"FCE4",
	"𣈲":"94AF",
	"𣈳":"FA77",
	"𣈴":"93CC",
	"𣉖":"8CE1",
	"𣉞":"87A9",
	"𣉢":"905A",
	"𣊁":"8C54",
	"𣊉":"93BF",
	"𣊊":"FB51",
	"𣊫":"93B9",
	"𣊬":"FED7",
	"𣊭":"93B7",
	"𣋒":"93D9",
	"𣋠":"93BB",
	"𣋡":"93DA",
	"𣌀":"98A3",
	"𣌊":"90D1",
	"𣌟":"9B6E",
	"𣎴":"FA70",
	"𣏌":"9BEB",
	"𣏞":"9B6F",
	"𣏦":"FCFC",
	"𣏴":"8B40",
	"𣏵":"A07B",
	"𣏹":"8CA1",
	"𣏺":"97F7",
	"𣏾":"93E2",
	"𣐀":"FCD6",
	"𣐿":"9559",
	"𣑐":"93A6",
	"𣑯":"FD40",
	"𣑲":"935F",
	"𣓥":"97F2",
	"𣔙":"9C76",
	"𣔰":"8EF8",
	"𣕑":"8CEB",
	"𣕚":"8F47",
	"𣕧":"9B74",
	"𣖕":"92B4",
	"𣖙":"91ED",
	"𣖜":"96D2",
	"𣖻":"87D8",
	"𣗍":"FD46",
	"𣗎":"8F4F",
	"𣗏":"9549",
	"𣗳":"9B75",
	"𣘀":"FA5C",
	"𣘗":"8751",
	"𣘚":"9B79",
	"𣘼":"FD4B",
	"𣙀":"96D3",
	"𣙙":"FD58",
	"𣙟":"945F",
	"𣙷":"A0F5",
	"𣚎":"87C7",
	"𣚞":"877C",
	"𣚦":"9243",
	"𣚭":"97FA",
	"𣚺":"9DD9",
	"𣛟":"97F4",
	"𣛮":"924D",
	"𣜃":"FD5B",
	"𣜖":"9B7A",
	"𣜠":"9ED5",
	"𣜭":"FAAE",
	"𣜯":"9CC9",
	"𣜿":"9258",
	"𣝦":"8EC8",
	"𣞁":"94B4",
	"𣞢":"93E1",
	"𣞼":"93DF",
	"𣟂":"FCF0",
	"𣟕":"93EC",
	"𣟖":"97F6",
	"𣟗":"96CF",
	"𣠺":"93DE",
	"𣧂":"8ACF",
	"𣪧":"9BA2",
	"𣫛":"FD69",
	"𣫮":"9352",
	"𣫺":"98A2",
	"𣬚":"8CE7",
	"𣭚":"FD6E",
	"𣱣":"8CA4",
	"𣲙":"FA7C",
	"𣲚":"93FA",
	"𣲛":"907C",
	"𣲵":"8F67",
	"𣲷":"9DB7",
	"𣳇":"A0E9",
	"𣳈":"FA4E",
	"𣳉":"FDA1",
	"𣳼":"9E74",
	"𣳽":"9FBF",
	"𣳾":"9ECB",
	"𣳿":"9BB9",
	"𣵀":"9DD4",
	"𣵛":"97B9",
	"𣵾":"8EF1",
	"𣶏":"957B",
	"𣶶":"9ED2",
	"𣶷":"9753",
	"𣶸":"96A4",
	"𣶹":"8FBE",
	"𣶺":"94D9",
	"𣶻":"9058",
	"𣶼":"FD79",
	"𣶽":"FD7B",
	"𣷣":"8EDA",
	"𣷸":"8EFA",
	"𣸆":"8762",
	"𣸑":"9BA5",
	"𣸬":"9ED9",
	"𣸭":"97D4",
	"𣸮":"90BB",
	"𣸯":"FDBC",
	"𣸰":"FDC6",
	"𣸱":"9248",
	"𣸹":"92B5",
	"𣺈":"9DC1",
	"𣺉":"92B9",
	"𣺊":"92A6",
	"𣺋":"8F4B",
	"𣺹":"9BA6",
	"𣺿":"92B6",
	"𣻗":"8E40",
	"𣻷":"9ED8",
	"𣻸":"945E",
	"𣻹":"985F",
	"𣻺":"94CE",
	"𣻻":"924A",
	"𣻼":"FD70",
	"𣼵":"9467",
	"𣽁":"8DEC",
	"𣽊":"9BD8",
	"𣽡":"8763",
	"𣽿":"9448",
	"𣾀":"FAC1",
	"𣾁":"9CF7",
	"𣾂":"FDBE",
	"𣾏":"8FDA",
	"𣾴":"FDD9",
	"𣾷":"FC7E",
	"𣿀":"93F9",
	"𣿅":"FA43",
	"𣿫":"FAEB",
	"𣿬":"FAC3",
	"𣿭":"97D3",
	"𣿮":"95F9",
	"𣿯":"9C48",
	"𣿰":"FDD8",
	"𤀑":"A0D8",
	"𤀹":"FDD7",
	"𤀺":"FB4A",
	"𤀻":"9BAF",
	"𤀼":"944B",
	"𤀽":"FDC9",
	"𤁗":"8EAC",
	"𤂅":"FDB2",
	"𤂋":"925A",
	"𤂌":"FCBD",
	"𤂍":"92D9",
	"𤂑":"FDD5",
	"𤃉":"92DD",
	"𤃡":"9259",
	"𤃬":"8CF0",
	"𤄄":"96BA",
	"𤄏":"925B",
	"𤄙":"9BAB",
	"𤄿":"FDDA",
	"𤅀":"FDDE",
	"𤅄":"FDD3",
	"𤅎":"8C46",
	"𤅕":"FDD6",
	"𤅖":"FDDC",
	"𤅗":"FDDD",
	"𤅜":"90FE",
	"𤅟":"FEA1",
	"𤅡":"87A5",
	"𤅷":"8BAD",
	"𤅺":"9CD8",
	"𤆣":"9E6D",
	"𤆤":"FD7C",
	"𤆥":"FB61",
	"𤆬":"96F8",
	"𤆵":"96F0",
	"𤇍":"FCF4",
	"𤇢":"FE60",
	"𤇼":"9852",
	"𤈛":"964F",
	"𤉋":"916E",
	"𤉖":"986D",
	"𤉙":"9864",
	"𤉶":"9453",
	"𤉷":"FDEC",
	"𤉸":"FB78",
	"𤊄":"95BA",
	"𤊓":"985D",
	"𤊕":"92F9",
	"𤊥":"985A",
	"𤊿":"8750",
	"𤋁":"FDF6",
	"𤋉":"93D0",
	"𤋊":"9862",
	"𤋮":"9BAD",
	"𤋺":"974F",
	"𤌍":"9BAE",
	"𤌚":"9452",
	"𤌴":"9BB0",
	"𤍈":"91D2",
	"𤍢":"97EA",
	"𤍣":"FB6B",
	"𤍤":"91B1",
	"𤍥":"FDF3",
	"𤎌":"92CB",
	"𤎖":"9BB1",
	"𤎜":"FCEC",
	"𤎽":"986B",
	"𤏁":"9751",
	"𤏩":"9871",
	"𤏪":"95EF",
	"𤏲":"9EF3",
	"𤏸":"91E8",
	"𤐄":"9BBA",
	"𤐵":"FB4C",
	"𤐶":"926A",
	"𤑚":"FDF8",
	"𤑛":"9861",
	"𤑳":"91E7",
	"𤒇":"93ED",
	"𤒈":"9744",
	"𤒹":"91E1",
	"𤒼":"FBF5",
	"𤓎":"9869",
	"𤓓":"8A62",
	"𤓖":"9BBB",
	"𤔅":"8CA8",
	"𤔡":"9C55",
	"𤕸":"8E77",
	"𤗈":"8AB2",
	"𤘘":"9EBC",
	"𤘪":"93E6",
	"𤙥":"93A2",
	"𤙴":"9BBD",
	"𤚗":"94B3",
	"𤛔":"937D",
	"𤜆":"9E66",
	"𤜥":"9459",
	"𤜯":"9BBF",
	"𤞏":"9458",
	"𤟠":"9EA5",
	"𤠒":"9BC7",
	"𤠣":"FE54",
	"𤢂":"8E74",
	"𤣩":"8BD6",
	"𤣰":"94B6",
	"𤣱":"FD74",
	"𤣲":"98C0",
	"𤣳":"94A5",
	"𤣻":"9BC8",
	"𤣿":"95ED",
	"𤤀":"FD7E",
	"𤤁":"FBEB",
	"𤤌":"FD7D",
	"𤤖":"976F",
	"𤤗":"9461",
	"𤤙":"9FC1",
	"𤤯":"95D7",
	"𤤳":"FA52",
	"𤤴":"9C58",
	"𤤾":"9F68",
	"𤤿":"9BE7",
	"𤥀":"FCCE",
	"𤥁":"96E8",
	"𤥂":"FA49",
	"𤥃":"97A1",
	"𤥢":"954D",
	"𤥣":"9EF8",
	"𤥴":"FE49",
	"𤥵":"91CE",
	"𤥶":"9771",
	"𤥻":"8CCF",
	"𤥿":"FDB1",
	"𤦂":"FC6E",
	"𤦈":"9CF2",
	"𤦉":"93B8",
	"𤦊":"9043",
	"𤦋":"9759",
	"𤦌":"94D7",
	"𤦍":"FE66",
	"𤦎":"947D",
	"𤦏":"FC6F",
	"𤦔":"9246",
	"𤦤":"FA6D",
	"𤦧":"8EF7",
	"𤦩":"FBB7",
	"𤦫":"947C",
	"𤦬":"92CD",
	"𤦭":"97B2",
	"𤦷":"FE65",
	"𤦸":"967E",
	"𤦹":"9758",
	"𤦺":"9B77",
	"𤦻":"91CF",
	"𤧅":"94A4",
	"𤧐":"9CAD",
	"𤧚":"8BAB",
	"𤧞":"96D5",
	"𤧟":"FCB3",
	"𤧣":"93AE",
	"𤧥":"976D",
	"𤧬":"9446",
	"𤧭":"95F7",
	"𤧶":"9C46",
	"𤧷":"955B",
	"𤧸":"91D1",
	"𤧹":"94F4",
	"𤧻":"FE67",
	"𤨎":"92A5",
	"𤨒":"FEDF",
	"𤨓":"8CAB",
	"𤨕":"9BC9",
	"𤨡":"FCED",
	"𤨢":"FDFA",
	"𤨣":"FCC8",
	"𤨤":"FE62",
	"𤨥":"91FC",
	"𤨦":"FE6B",
	"𤨧":"FDF9",
	"𤨨":"FCC7",
	"𤨩":"914E",
	"𤨪":"9CB8",
	"𤨾":"9767",
	"𤩂":"95EE",
	"𤩅":"9BB2",
	"𤩊":"9460",
	"𤩎":"94A2",
	"𤩏":"9875",
	"𤩐":"97AC",
	"𤩑":"91D3",
	"𤩝":"987B",
	"𤩥":"8EEB",
	"𤩦":"976A",
	"𤩧":"965E",
	"𤩱":"97EB",
	"𤩷":"9FF9",
	"𤩸":"95F8",
	"𤩹":"FEA2",
	"𤩺":"8FE6",
	"𤪌":"FE7E",
	"𤪓":"9DA4",
	"𤪔":"9768",
	"𤪕":"8EEC",
	"𤪖":"94BD",
	"𤪤":"945B",
	"𤪥":"9CF6",
	"𤪦":"FAA7",
	"𤪧":"9BD9",
	"𤪱":"FA5D",
	"𤪲":"9656",
	"𤪳":"9762",
	"𤪺":"94BA",
	"𤪻":"A04F",
	"𤪼":"92D8",
	"𤫀":"9BCB",
	"𤫇":"94BB",
	"𤫊":"9D5F",
	"𤫑":"90CF",
	"𤫟":"9465",
	"𤫢":"9F4C",
	"𤫩":"90D8",
	"𤬏":"8D5B",
	"𤭮":"9EBE",
	"𤯵":"FB6D",
	"𤰉":"95CA",
	"𤲞":"9DC2",
	"𤲟":"97F8",
	"𤳉":"8FFC",
	"𤳙":"9473",
	"𤴆":"9474",
	"𤴓":"FEB7",
	"𤶸":"8A4B",
	"𤷪":"8A55",
	"𤷫":"8B69",
	"𤸻":"8ADC",
	"𤹐":"8B76",
	"𤺥":"9BCE",
	"𤺧":"8A68",
	"𤼎":"A0F8",
	"𤽜":"98DF",
	"𤾂":"FEB5",
	"𤾆":"9BCF",
	"𤾗":"96FB",
	"𤾚":"9BFB",
	"𤾩":"9ECE",
	"𤾸":"8EE5",
	"𤿂":"9E7B",
	"𥀬":"9BD2",
	"𥁒":"8AA5",
	"𥂝":"FECE",
	"𥄫":"8A45",
	"𥅈":"9DFC",
	"𥅽":"FECF",
	"𥅾":"8BA5",
	"𥇍":"8C4A",
	"𥇣":"8AEC",
	"𥇦":"FCE0",
	"𥇧":"94AD",
	"𥈠":"FED5",
	"𥈡":"94AC",
	"𥉐":"FC5A",
	"𥊙":"9BD6",
	"𥋇":"8A6F",
	"𥋘":"8BA9",
	"𥌎":"8E5F",
	"𥌑":"9DCB",
	"𥌓":"FCE7",
	"𥐙":"9BD7",
	"𥐥":"93C8",
	"𥐯":"91F0",
	"𥐰":"8FE0",
	"𥑆":"9BDB",
	"𥑬":"90ED",
	"𥑮":"9BDC",
	"𥒚":"8D53",
	"𥔱":"A0EC",
	"𥔵":"98FA",
	"𥔿":"9BE0",
	"𥕛":"93C7",
	"𥕜":"9249",
	"𥕝":"96E1",
	"𥕞":"9BE2",
	"𥕢":"9BE4",
	"𥕥":"8FE1",
	"𥕦":"9BE5",
	"𥖁":"94C0",
	"𥖄":"93C3",
	"𥖏":"93C5",
	"𥖹":"9079",
	"𥗕":"977B",
	"𥗛":"907E",
	"𥗠":"FEE6",
	"𥘅":"FE46",
	"𥘵":"9DB8",
	"𥙑":"9270",
	"𥚃":"95A8",
	"𥚕":"8CB0",
	"𥛣":"94C8",
	"𥛶":"98B9",
	"𥜆":"9140",
	"𥜝":"FCBE",
	"𥜥":"9157",
	"𥜽":"8BB2",
	"𥝲":"FADF",
	"𥟇":"9BE6",
	"𥟟":"9643",
	"𥟠":"8E44",
	"𥟡":"9C4F",
	"𥡗":"FEF4",
	"𥡝":"9BE8",
	"𥡲":"93DC",
	"𥣈":"966F",
	"𥣞":"87A1",
	"𥣡":"8E4A",
	"𥤃":"9BED",
	"𥥆":"92F6",
	"𥥖":"9DB9",
	"𥦬":"8E4E",
	"𥧌":"FBCF",
	"𥩔":"8760",
	"𥪕":"9EC2",
	"𥪜":"94E5",
	"𥪮":"9BF0",
	"𥪯":"94E4",
	"𥫩":"9551",
	"𥭴":"8BBB",
	"𥮉":"9BF1",
	"𥮳":"94F0",
	"𥮴":"8E64",
	"𥯆":"94EA",
	"𥯤":"8F61",
	"𥯨":"9B64",
	"𥰁":"8E5B",
	"𥰆":"9BF2",
	"𥰡":"9FBE",
	"𥱊":"9DC9",
	"𥱥":"8E6C",
	"𥲑":"8F73",
	"𥲤":"8CAF",
	"𥳀":"8F75",
	"𥳁":"8E71",
	"𥳾":"8E60",
	"𥴠":"8E6A",
	"𥴰":"8C4C",
	"𥵃":"9552",
	"𥶙":"87CF",
	"𥶹":"87C0",
	"𥸎":"9554",
	"𥹉":"8AD4",
	"𥺁":"9DBB",
	"𥺂":"9543",
	"𥺃":"92FE",
	"𥺦":"94F2",
	"𥺼":"94F1",
	"𥻗":"A0EA",
	"𥻘":"9DD2",
	"𥼚":"A0B1",
	"𥽋":"91F8",
	"𥿡":"9462",
	"𥿢":"9BA4",
	"𦀡":"877D",
	"𦀩":"8EAD",
	"𦁈":"9EAD",
	"𦁤":"96D0",
	"𦂃":"FEEE",
	"𦂗":"8AB4",
	"𦂤":"9757",
	"𦂥":"8A77",
	"𦄂":"9BF7",
	"𦄡":"8EB5",
	"𦅙":"A06D",
	"𦅚":"8EB6",
	"𦅛":"9756",
	"𦅜":"9540",
	"𦆭":"A0F3",
	"𦆮":"94BE",
	"𦆲":"9BFA",
	"𦇝":"FDDF",
	"𦉘":"9DBC",
	"𦉡":"94FE",
	"𦉪":"8BDB",
	"𦉫":"A0FE",
	"𦋐":"8EC0",
	"𦌵":"9F47",
	"𦍋":"8BDE",
	"𦍌":"A0FB",
	"𦍑":"8EC3",
	"𦎾":"9649",
	"𦏵":"FEC2",
	"𦏸":"954C",
	"𦐂":"9BFD",
	"𦐐":"90CC",
	"𦐑":"9C60",
	"𦐒":"954B",
	"𦑊":"9BFE",
	"𦑩":"9C70",
	"𦒄":"9C43",
	"𦒈":"9C47",
	"𦒉":"8ECC",
	"𦒍":"8E54",
	"𦒘":"8EE4",
	"𦔒":"9C49",
	"𦕲":"8B5E",
	"𦖠":"955E",
	"𦖭":"955C",
	"𦖿":"9C4B",
	"𦘒":"8BE1",
	"𦘦":"8ED9",
	"𦚯":"9DB4",
	"𦚱":"925F",
	"𦚵":"9C4C",
	"𦛚":"8AA1",
	"𦛨":"8EDB",
	"𦛼":"9C56",
	"𦜖":"8AA2",
	"𦝁":"9754",
	"𦞙":"9C5E",
	"𦞳":"9ED4",
	"𦞴":"9568",
	"𦟌":"A0C3",
	"𦠜":"8AE6",
	"𦡆":"A0F7",
	"𦡞":"9C61",
	"𦡮":"9C5F",
	"𦢈":"FC4D",
	"𦢊":"9E5B",
	"𦢓":"9E69",
	"𦣇":"9C63",
	"𦤎":"FEC7",
	"𦤑":"FEC6",
	"𦤦":"9C67",
	"𦤹":"9C69",
	"𦥑":"8BE2",
	"𦦨":"9165",
	"𦦵":"9CE7",
	"𦧲":"8A54",
	"𦧺":"9C6C",
	"𦨭":"9C6E",
	"𦨮":"FE5D",
	"𦨴":"9C73",
	"𦩂":"956A",
	"𦩑":"956D",
	"𦩒":"8EF0",
	"𦬅":"8F4D",
	"𦬊":"8EF6",
	"𦬓":"FABC",
	"𦬕":"8CD5",
	"𦬣":"875E",
	"𦬨":"FBDA",
	"𦭐":"8B4C",
	"𦭑":"FD75",
	"𦭒":"9BDD",
	"𦭓":"FAF5",
	"𦭛":"9C74",
	"𦭵":"9545",
	"𦮂":"96C6",
	"𦮖":"8F6A",
	"𦮗":"8F4E",
	"𦮝":"9C78",
	"𦮳":"FA55",
	"𦯀":"97E4",
	"𦯷":"9C41",
	"𦰡":"925C",
	"𦱀":"96FA",
	"𦱁":"8CF6",
	"𦱆":"8D4D",
	"𦱾":"FB66",
	"𦱿":"8E65",
	"𦲀":"9849",
	"𦲁":"FBA8",
	"𦲂":"9842",
	"𦲤":"9C7A",
	"𦲷":"97FB",
	"𦲸":"90CA",
	"𦲽":"9C5B",
	"𦳀":"974D",
	"𦳃":"8ED3",
	"𦳑":"9561",
	"𦴢":"9F4B",
	"𦴣":"9FB5",
	"𦴤":"93D2",
	"𦴥":"FDAA",
	"𦴦":"9840",
	"𦴧":"9146",
	"𦴨":"9867",
	"𦴩":"FA5A",
	"𦴪":"FBA9",
	"𦵑":"9841",
	"𦵴":"8CD3",
	"𦶠":"FCFD",
	"𦶡":"FDAB",
	"𦶢":"91BD",
	"𦶣":"8F4C",
	"𦶤":"96C9",
	"𦶥":"8F55",
	"𦶦":"FBAE",
	"𦶧":"956F",
	"𦶮":"9C7D",
	"𦷜":"A0F0",
	"𦷪":"946F",
	"𦷫":"FDAC",
	"𦷰":"96CB",
	"𦸀":"96CE",
	"𦸅":"A056",
	"𦸇":"9CE1",
	"𦸒":"96C4",
	"𦹂":"8F5E",
	"𦹃":"8F6C",
	"𦹄":"8EA3",
	"𦹅":"FBB3",
	"𦹮":"FC53",
	"𦹲":"FDB3",
	"𦹷":"8F6B",
	"𦺄":"96CA",
	"𦺈":"87CD",
	"𦺋":"8753",
	"𦺙":"8F79",
	"𦻐":"9E6F",
	"𦻑":"A0C5",
	"𦻒":"FC78",
	"𦻓":"8E42",
	"𦻔":"8F5A",
	"𦻕":"90C2",
	"𦻖":"8EA5",
	"𦻗":"9061",
	"𦼦":"924F",
	"𦽳":"9373",
	"𦽴":"FDB5",
	"𦾟":"FECC",
	"𦾡":"FBBD",
	"𦾾":"8CD6",
	"𦿞":"9843",
	"𦿟":"96C5",
	"𧀎":"89BC",
	"𧁋":"9CA3",
	"𧁒":"924B",
	"𧁓":"984A",
	"𧂈":"8FA4",
	"𧂭":"A0F1",
	"𧂮":"9EFB",
	"𧂯":"9CD2",
	"𧃍":"8FA7",
	"𧃒":"8754",
	"𧃸":"FC5C",
	"𧄉":"9845",
	"𧄌":"9046",
	"𧄍":"8CD1",
	"𧄦":"FEFA",
	"𧄧":"9560",
	"𧅤":"9F48",
	"𧅥":"9247",
	"𧅵":"90FB",
	"𧇍":"9CA4",
	"𧈛":"9571",
	"𧉧":"8745",
	"𧊀":"9CA6",
	"𧊅":"9CA7",
	"𧊋":"9CAA",
	"𧊲":"9ED3",
	"𧊶":"9E70",
	"𧋦":"9CAC",
	"𧍒":"8752",
	"𧎚":"8FAE",
	"𧏿":"8D50",
	"𧐢":"957D",
	"𧑐":"9CB0",
	"𧒄":"97B6",
	"𧒆":"A0BD",
	"𧕴":"8ADF",
	"𧖣":"9EAA",
	"𧗠":"8FBD",
	"𧗤":"8FBF",
	"𧗽":"9369",
	"𧗾":"9BA7",
	"𧘇":"C8A4",
	"𧘌":"FEEA",
	"𧘲":"9BE1",
	"𧘹":"8B41",
	"𧙕":"9DB6",
	"𧙖":"A0EB",
	"𧙗":"9BA3",
	"𧚔":"8BA1",
	"𧜏":"8FC8",
	"𧜵":"894C",
	"𧜶":"9860",
	"𧝁":"94C7",
	"𧝞":"8B58",
	"𧞄":"95AB",
	"𧞅":"95AA",
	"𧟌":"9CC3",
	"𧡘":"9CC4",
	"𧡰":"93D6",
	"𧢝":"9DAC",
	"𧢲":"8BE6",
	"𧣈":"8A71",
	"𧤤":"8FD1",
	"𧥧":"99D5",
	"𧥺":"90F4",
	"𧦠":"8AA3",
	"𧧝":"9CCE",
	"𧧽":"9CD4",
	"𧨊":"9CD5",
	"𧨎":"FBC8",
	"𧨾":"9DB3",
	"𧩓":"FC70",
	"𧩙":"8FD7",
	"𧩹":"9B73",
	"𧪄":"FA5B",
	"𧪽":"8FD2",
	"𧪾":"9064",
	"𧫴":"98B6",
	"𧬆":"9668",
	"𧬋":"9CD6",
	"𧬘":"98BD",
	"𧬸":"8FDC",
	"𧬹":"FEF6",
	"𧬺":"8FD9",
	"𧭈":"9541",
	"𧭥":"87CA",
	"𧯯":"876C",
	"𧯴":"97F3",
	"𧰒":"9BF8",
	"𧱬":"875A",
	"𧲱":"8748",
	"𧳅":"874A",
	"𧴯":"9E6C",
	"𧵓":"8FF2",
	"𧵔":"8FEE",
	"𧵦":"9CD7",
	"𧵳":"9E6E",
	"𧶄":"8A40",
	"𧶏":"8FEF",
	"𧶘":"8FF4",
	"𧶽":"8FF5",
	"𧷜":"95C2",
	"𧹍":"986A",
	"𧹏":"97CF",
	"𧼮":"9EE5",
	"𧿹":"9E7C",
	"𨀂":"9041",
	"𨀉":"9CDB",
	"𨀞":"9441",
	"𨀣":"9CE6",
	"𨀤":"9DB0",
	"𨁈":"9CEA",
	"𨂃":"9CED",
	"𨂐":"9CFA",
	"𨂽":"8B62",
	"𨂾":"8A4E",
	"𨃨":"9CCA",
	"𨃩":"8A66",
	"𨃴":"9CFB",
	"𨄮":"9CFC",
	"𨅏":"9CFE",
	"𨅝":"8A53",
	"𨅯":"9CE5",
	"𨆉":"9D40",
	"𨆯":"9D41",
	"𨆼":"9045",
	"𨈇":"8B73",
	"𨈘":"97CA",
	"𨈚":"9D42",
	"𨉖":"8A61",
	"𨉼":"8BAE",
	"𨊛":"8AD2",
	"𨋍":"8BA2",
	"𨋢":"9DF2",
	"𨌆":"9D43",
	"𨌘":"9CDF",
	"𨌯":"9D44",
	"𨌺":"8ECA",
	"𨍥":"904E",
	"𨍭":"8EB3",
	"𨍽":"9FF5",
	"𨎊":"9D45",
	"𨐒":"904F",
	"𨑨":"9D47",
	"𨑬":"89CA",
	"𨑳":"9CB5",
	"𨒂":"FBFE",
	"𨔁":"905E",
	"𨔼":"9063",
	"𨔽":"9057",
	"𨕬":"9066",
	"𨗨":"9BC0",
	"𨗴":"FCE5",
	"𨘀":"9162",
	"𨘋":"9067",
	"𨘥":"8FA1",
	"𨘻":"8FA2",
	"𨚪":"9D48",
	"𨚫":"FAD3",
	"𨚲":"8D4F",
	"𨚼":"905D",
	"𨛘":"90B9",
	"𨛦":"906B",
	"𨜏":"8C5C",
	"𨜓":"9069",
	"𨠄":"FE57",
	"𨠫":"FE55",
	"𨤍":"87A6",
	"𨤳":"9073",
	"𨥈":"9BEF",
	"𨥉":"9CF0",
	"𨥖":"9D4B",
	"𨥤":"FED9",
	"𨥨":"FEDA",
	"𨥬":"91E0",
	"𨥭":"8D43",
	"𨥾":"91D8",
	"𨦉":"9646",
	"𨦨":"9360",
	"𨦪":"FA53",
	"𨦫":"9CD3",
	"𨦸":"9D4E",
	"𨦼":"FB40",
	"𨧀":"8DE2",
	"𨧜":"9442",
	"𨧞":"9056",
	"𨧡":"9865",
	"𨧣":"8C6C",
	"𨧤":"FA4A",
	"𨧧":"9D50",
	"𨧨":"9D52",
	"𨧹":"95AF",
	"𨧺":"975A",
	"𨧻":"9349",
	"𨧼":"9747",
	"𨨏":"A0F4",
	"𨨖":"9778",
	"𨨥":"8FCF",
	"𨨩":"FC60",
	"𨨲":"8C4E",
	"𨨶":"FC56",
	"𨩄":"91DC",
	"𨩅":"9661",
	"𨩆":"92EC",
	"𨩇":"935D",
	"𨩈":"8EDE",
	"𨩉":"96FE",
	"𨩊":"FD4F",
	"𨩋":"95DE",
	"𨩙":"98B0",
	"𨩚":"A040",
	"𨪁":"97BD",
	"𨪂":"977D",
	"𨪃":"97F5",
	"𨪚":"9BAC",
	"𨪛":"FADA",
	"𨪜":"92C2",
	"𨫀":"97B1",
	"𨫆":"907B",
	"𨫋":"93FE",
	"𨫌":"947B",
	"𨫎":"9777",
	"𨫞":"FABE",
	"𨫟":"FD43",
	"𨫠":"90C6",
	"𨫡":"90A4",
	"𨫢":"90A8",
	"𨫣":"94A9",
	"𨫥":"90A9",
	"𨫪":"8C65",
	"𨫼":"95E0",
	"𨬌":"907D",
	"𨬓":"9265",
	"𨬡":"FDBA",
	"𨬢":"93C4",
	"𨬫":"FEED",
	"𨬬":"9DAB",
	"𨬭":"A0E3",
	"𨬯":"9648",
	"𨭆":"9D53",
	"𨭌":"8AA9",
	"𨭎":"9BC5",
	"𨭐":"965D",
	"𨭣":"975F",
	"𨭤":"965F",
	"𨭥":"966E",
	"𨭦":"FB5D",
	"𨭬":"9DB1",
	"𨮏":"FEA3",
	"𨮙":"9DB2",
	"𨮜":"95AE",
	"𨮝":"FCA3",
	"𨮹":"8769",
	"𨯂":"A0A2",
	"𨯅":"9655",
	"𨯔":"9D54",
	"𨯗":"9341",
	"𨯙":"95AD",
	"𨯚":"91D5",
	"𨯧":"977A",
	"𨯨":"FDFC",
	"𨯩":"8E47",
	"𨯪":"93FD",
	"𨯫":"90A5",
	"𨯬":"90AC",
	"𨯵":"95AC",
	"𨯿":"90AE",
	"𨰃":"FEA5",
	"𨰉":"9D56",
	"𨰜":"97E3",
	"𨰝":"95E2",
	"𨰣":"9466",
	"𨰦":"9647",
	"𨰫":"91B8",
	"𨰰":"9CEC",
	"𨰹":"90AD",
	"𨰻":"95E3",
	"𨳊":"8B4F",
	"𨳍":"8AE3",
	"𨳒":"8B4D",
	"𨴴":"95EA",
	"𨶙":"8B4E",
	"𨶹":"8CC1",
	"𨸏":"8BED",
	"𨸶":"91D9",
	"𨸹":"A0A4",
	"𨹥":"95F5",
	"𨹦":"95F4",
	"𨺗":"9FB3",
	"𨺬":"FEAF",
	"𨺲":"FE72",
	"𨺳":"927A",
	"𨻙":"FEAC",
	"𨻧":"95F3",
	"𨿅":"9D58",
	"𩁹":"8D46",
	"𩂈":"9372",
	"𩂋":"91C5",
	"𩂓":"9642",
	"𩂯":"90CD",
	"𩂰":"95FE",
	"𩂱":"9159",
	"𩃀":"9C65",
	"𩃤":"97CC",
	"𩃥":"90CE",
	"𩃬":"9D59",
	"𩃭":"FCF5",
	"𩄍":"FEFD",
	"𩄐":"9D5B",
	"𩄼":"9D5C",
	"𩅍":"937E",
	"𩅛":"98AC",
	"𩅞":"9D5E",
	"𩅰":"FDD0",
	"𩆜":"FD60",
	"𩆨":"9CCF",
	"𩇕":"90DD",
	"𩇫":"90E0",
	"𩐝":"90F3",
	"𩐠":"98B1",
	"𩐳":"90F0",
	"𩐿":"93BD",
	"𩑈":"95B7",
	"𩓐":"9F46",
	"𩓙":"8E4B",
	"𩓚":"9658",
	"𩓥":"8A4C",
	"𩓧":"9D63",
	"𩖞":"9ECF",
	"𩖰":"9D65",
	"𩖸":"9D66",
	"𩗗":"965A",
	"𩗩":"9D64",
	"𩗴":"8A6C",
	"𩜠":"8AD9",
	"𩜲":"9D67",
	"𩟔":"8A70",
	"𩠐":"8BF3",
	"𩡗":"9150",
	"𩢤":"9CC1",
	"𩣑":"9D68",
	"𩣪":"93A7",
	"𩣱":"9674",
	"𩣺":"8CFD",
	"𩤃":"A0EF",
	"𩤅":"9151",
	"𩤯":"96C1",
	"𩥅":"8777",
	"𩥇":"8C64",
	"𩥈":"9676",
	"𩥉":"9D69",
	"𩥝":"FCA4",
	"𩥪":"9D6A",
	"𩦝":"924E",
	"𩧃":"9D6B",
	"𩧉":"9BC1",
	"𩨨":"9D6C",
	"𩩍":"8A65",
	"𩬅":"915D",
	"𩬎":"9D6D",
	"𩯕":"915A",
	"𩱳":"8C42",
	"𩲭":"9CC0",
	"𩴾":"916A",
	"𩵚":"9D6E",
	"𩵼":"9EA6",
	"𩶘":"9DCD",
	"𩶛":"9D6F",
	"𩷶":"89BB",
	"𩸆":"9EF9",
	"𩸭":"96B4",
	"𩹨":"9172",
	"𩺬":"9EC8",
	"𩺰":"8771",
	"𩻃":"8B55",
	"𩻸":"9D71",
	"𩼣":"9D72",
	"𩼰":"9ECC",
	"𩾷":"9174",
	"𩿞":"9ED0",
	"𪀔":"905C",
	"𪂇":"8ED2",
	"𪂹":"91A8",
	"𪃡":"9177",
	"𪃭":"96BF",
	"𪃳":"96C0",
	"𪃸":"8FB1",
	"𪃾":"96B7",
	"𪄇":"8C55",
	"𪄣":"9178",
	"𪄳":"89BE",
	"𪄴":"917C",
	"𪅐":"FB77",
	"𪆒":"9175",
	"𪆓":"91A3",
	"𪆫":"9176",
	"𪆴":"96BE",
	"𪆵":"8D49",
	"𪇟":"9179",
	"𪇵":"96B6",
	"𪈠":"91A4",
	"𪈳":"91A6",
	"𪊓":"9D75",
	"𪊟":"9052",
	"𪊲":"A045",
	"𪊴":"91A9",
	"𪊶":"98AA",
	"𪊺":"8C5F",
	"𪊽":"8BAA",
	"𪋟":"9CDD",
	"𪋿":"9D77",
	"𪍑":"8756",
	"𪎩":"8940",
	"𪐴":"9EEC",
	"𪑛":"93AA",
	"𪗆":"9478",
	"𪗋":"9D7A",
	"𪘁":"8AC9",
	"𪘲":"8B4B",
	"𪙊":"9FEC",
	"𪙛":"8AE2",
	"𪚩":"9E75",
	"𪷿":"87DC",
	"勇":"9874",
	"吆":"9AC8",
	"咢":"A047",
	"屮":"8BC3",
	"弢":"FC48",
	"慈":"FC77",
	"晉":"9C52",
	"芳":"8EFD",
	"䕫":"8FA8",
	"蜨":"957A",
	"貫":"8FF0"
}
